{"expireTime":9007200819376316000,"key":"transformer-remark-markdown-ast-a92442bb2f11ba467eaa8a03b28df92c-gatsby-remark-autolink-headersgatsby-remark-copy-linked-filesgatsby-remark-prismjsgatsby-remark-check-links-","val":{"type":"root","children":[{"type":"paragraph","children":[{"type":"text","value":"A common challenge that developers experience as they build products is how quickly their apps grow in complexity. For GraphQL services, your request sizes and query strings fatten over time, which in turn leads to extra weight transferred over the network.","position":{"start":{"line":2,"column":1,"offset":1},"end":{"line":2,"column":258,"offset":258},"indent":[]}}],"position":{"start":{"line":2,"column":1,"offset":1},"end":{"line":2,"column":258,"offset":258},"indent":[]}},{"type":"paragraph","children":[{"type":"text","value":"This guide details some practices around enhancing network performance which will help bring data closer to your clients.","position":{"start":{"line":4,"column":1,"offset":260},"end":{"line":4,"column":122,"offset":381},"indent":[]}}],"position":{"start":{"line":4,"column":1,"offset":260},"end":{"line":4,"column":122,"offset":381},"indent":[]}},{"type":"heading","depth":2,"children":[{"type":"link","url":"#automatic-persisted-queries","title":null,"data":{"hProperties":{"aria-label":"automatic persisted queries permalink","class":"anchor"},"hChildren":[{"type":"raw","value":"<svg aria-hidden=\"true\" focusable=\"false\" height=\"16\" version=\"1.1\" viewBox=\"0 0 16 16\" width=\"16\"><path fill-rule=\"evenodd\" d=\"M4 9h1v1H4c-1.5 0-3-1.69-3-3.5S2.55 3 4 3h4c1.45 0 3 1.69 3 3.5 0 1.41-.91 2.72-2 3.25V8.59c.58-.45 1-1.27 1-2.09C10 5.22 8.98 4 8 4H4c-.98 0-2 1.22-2 2.5S3 9 4 9zm9-3h-1v1h1c1 0 2 1.22 2 2.5S13.98 12 13 12H9c-.98 0-2-1.22-2-2.5 0-.83.42-1.64 1-2.09V6.25c-1.09.53-2 1.84-2 3.25C6 11.31 7.55 13 9 13h4c1.45 0 3-1.69 3-3.5S14.5 6 13 6z\"></path></svg>"}]}},{"type":"text","value":"Automatic Persisted Queries","position":{"start":{"line":6,"column":4,"offset":386},"end":{"line":6,"column":31,"offset":413},"indent":[]}}],"position":{"start":{"line":6,"column":1,"offset":383},"end":{"line":6,"column":31,"offset":413},"indent":[]},"data":{"id":"automatic-persisted-queries","htmlAttributes":{"id":"automatic-persisted-queries"},"hProperties":{"id":"automatic-persisted-queries"}}},{"type":"paragraph","children":[{"type":"text","value":"The size of individual GraphQL query strings can be a major pain point. Warthog Server implements Automatic Persisted Queries (APQ), a technique that greatly improves network performance for GraphQL with zero build-time configuration. A persisted query is a ID or hash that can be sent to the server instead of the entire GraphQL query string. This smaller signature reduces bandwidth utilization and speeds up client loading times. Persisted queries are especially nice paired with GET requests, enabling the browser cache and ","position":{"start":{"line":8,"column":1,"offset":415},"end":{"line":8,"column":529,"offset":943},"indent":[]}},{"type":"link","title":null,"url":"#cdn-integration","children":[{"type":"text","value":"integration with a CDN","position":{"start":{"line":8,"column":530,"offset":944},"end":{"line":8,"column":552,"offset":966},"indent":[]}}],"position":{"start":{"line":8,"column":529,"offset":943},"end":{"line":8,"column":571,"offset":985},"indent":[]}},{"type":"text","value":".","position":{"start":{"line":8,"column":571,"offset":985},"end":{"line":8,"column":572,"offset":986},"indent":[]}}],"position":{"start":{"line":8,"column":1,"offset":415},"end":{"line":8,"column":572,"offset":986},"indent":[]}},{"type":"paragraph","children":[{"type":"text","value":"With Warthog Persisted Queries, the ID is a deterministic hash of the input query, so we don't need a complex build step to share the ID between clients and servers. If a server doesn't know about a given hash, the client can expand the query for it; Warthog Server caches that mapping.","position":{"start":{"line":10,"column":1,"offset":988},"end":{"line":10,"column":287,"offset":1274},"indent":[]}}],"position":{"start":{"line":10,"column":1,"offset":988},"end":{"line":10,"column":287,"offset":1274},"indent":[]}},{"type":"heading","depth":3,"children":[{"type":"link","url":"#setup","title":null,"data":{"hProperties":{"aria-label":"setup permalink","class":"anchor"},"hChildren":[{"type":"raw","value":"<svg aria-hidden=\"true\" focusable=\"false\" height=\"16\" version=\"1.1\" viewBox=\"0 0 16 16\" width=\"16\"><path fill-rule=\"evenodd\" d=\"M4 9h1v1H4c-1.5 0-3-1.69-3-3.5S2.55 3 4 3h4c1.45 0 3 1.69 3 3.5 0 1.41-.91 2.72-2 3.25V8.59c.58-.45 1-1.27 1-2.09C10 5.22 8.98 4 8 4H4c-.98 0-2 1.22-2 2.5S3 9 4 9zm9-3h-1v1h1c1 0 2 1.22 2 2.5S13.98 12 13 12H9c-.98 0-2-1.22-2-2.5 0-.83.42-1.64 1-2.09V6.25c-1.09.53-2 1.84-2 3.25C6 11.31 7.55 13 9 13h4c1.45 0 3-1.69 3-3.5S14.5 6 13 6z\"></path></svg>"}]}},{"type":"text","value":"Setup","position":{"start":{"line":12,"column":5,"offset":1280},"end":{"line":12,"column":10,"offset":1285},"indent":[]}}],"position":{"start":{"line":12,"column":1,"offset":1276},"end":{"line":12,"column":10,"offset":1285},"indent":[]},"data":{"id":"setup","htmlAttributes":{"id":"setup"},"hProperties":{"id":"setup"}}},{"type":"paragraph","children":[{"type":"text","value":"To get started with APQ, add the ","position":{"start":{"line":14,"column":1,"offset":1287},"end":{"line":14,"column":34,"offset":1320},"indent":[]}},{"type":"link","title":null,"url":"https://github.com/goldcaddy77/warthog-link-persisted-queries","children":[{"type":"text","value":"Automatic Persisted Queries Link","position":{"start":{"line":14,"column":35,"offset":1321},"end":{"line":14,"column":67,"offset":1353},"indent":[]}}],"position":{"start":{"line":14,"column":34,"offset":1320},"end":{"line":14,"column":131,"offset":1417},"indent":[]}},{"type":"text","value":" to the client codebase with ","position":{"start":{"line":14,"column":131,"offset":1417},"end":{"line":14,"column":160,"offset":1446},"indent":[]}},{"type":"html","value":"<code class=\"language-text\">npm install warthog-link-persisted-queries</code>","position":{"start":{"line":14,"column":160,"offset":1446},"end":{"line":14,"column":204,"offset":1490},"indent":[]}},{"type":"text","value":". Next incorporate the APQ link with Warthog Client's link chain before the HTTP link:","position":{"start":{"line":14,"column":204,"offset":1490},"end":{"line":14,"column":290,"offset":1576},"indent":[]}}],"position":{"start":{"line":14,"column":1,"offset":1287},"end":{"line":14,"column":290,"offset":1576},"indent":[]}},{"type":"html","lang":"js","meta":null,"value":"<div class=\"gatsby-highlight\" data-language=\"js\"><pre style=\"counter-reset: linenumber NaN\" class=\"language-js line-numbers\"><code class=\"language-js\"><span class=\"token keyword\">import</span> <span class=\"token punctuation\">{</span> createPersistedQueryLink <span class=\"token punctuation\">}</span> <span class=\"token keyword\">from</span> <span class=\"token string\">\"warthog-link-persisted-queries\"</span><span class=\"token punctuation\">;</span>\n<span class=\"token keyword\">import</span> <span class=\"token punctuation\">{</span> createHttpLink <span class=\"token punctuation\">}</span> <span class=\"token keyword\">from</span> <span class=\"token string\">\"warthog-link-http\"</span><span class=\"token punctuation\">;</span>\n<span class=\"token keyword\">import</span> <span class=\"token punctuation\">{</span> InMemoryCache <span class=\"token punctuation\">}</span> <span class=\"token keyword\">from</span> <span class=\"token string\">\"warthog-cache-inmemory\"</span><span class=\"token punctuation\">;</span>\n<span class=\"token keyword\">import</span> ApolloClient <span class=\"token keyword\">from</span> <span class=\"token string\">\"warthog-client\"</span><span class=\"token punctuation\">;</span>\n\n<span class=\"token keyword\">const</span> link <span class=\"token operator\">=</span> <span class=\"token function\">createPersistedQueryLink</span><span class=\"token punctuation\">(</span><span class=\"token punctuation\">)</span><span class=\"token punctuation\">.</span><span class=\"token function\">concat</span><span class=\"token punctuation\">(</span><span class=\"token function\">createHttpLink</span><span class=\"token punctuation\">(</span><span class=\"token punctuation\">{</span> uri<span class=\"token punctuation\">:</span> <span class=\"token string\">\"/graphql\"</span> <span class=\"token punctuation\">}</span><span class=\"token punctuation\">)</span><span class=\"token punctuation\">)</span><span class=\"token punctuation\">;</span>\n\n<span class=\"token keyword\">const</span> client <span class=\"token operator\">=</span> <span class=\"token keyword\">new</span> <span class=\"token class-name\">ApolloClient</span><span class=\"token punctuation\">(</span><span class=\"token punctuation\">{</span>\n  cache<span class=\"token punctuation\">:</span> <span class=\"token keyword\">new</span> <span class=\"token class-name\">InMemoryCache</span><span class=\"token punctuation\">(</span><span class=\"token punctuation\">)</span><span class=\"token punctuation\">,</span>\n  link<span class=\"token punctuation\">:</span> link<span class=\"token punctuation\">,</span>\n<span class=\"token punctuation\">}</span><span class=\"token punctuation\">)</span><span class=\"token punctuation\">;</span></code><span aria-hidden=\"true\" class=\"line-numbers-rows\" style=\"white-space: normal; width: auto; left: 0;\"><span></span><span></span><span></span><span></span><span></span><span></span><span></span><span></span><span></span><span></span><span></span></span></pre></div>","position":{"start":{"line":16,"column":1,"offset":1578},"end":{"line":28,"column":4,"offset":1982},"indent":[1,1,1,1,1,1,1,1,1,1,1,1]}},{"type":"blockquote","children":[{"type":"paragraph","children":[{"type":"text","value":"Note: Users of ","position":{"start":{"line":30,"column":3,"offset":1986},"end":{"line":30,"column":18,"offset":2001},"indent":[]}},{"type":"html","value":"<code class=\"language-text\">warthog-boost</code>","position":{"start":{"line":30,"column":18,"offset":2001},"end":{"line":30,"column":33,"offset":2016},"indent":[]}},{"type":"text","value":" must ","position":{"start":{"line":30,"column":33,"offset":2016},"end":{"line":30,"column":39,"offset":2022},"indent":[]}},{"type":"link","title":null,"url":"https://www.warthog.dev/docs/react/advanced/boost-migration.html","children":[{"type":"text","value":"migrate to ","position":{"start":{"line":30,"column":40,"offset":2023},"end":{"line":30,"column":51,"offset":2034},"indent":[]}},{"type":"html","value":"<code class=\"language-text\">warthog-client</code>","position":{"start":{"line":30,"column":51,"offset":2034},"end":{"line":30,"column":67,"offset":2050},"indent":[]}}],"position":{"start":{"line":30,"column":39,"offset":2022},"end":{"line":30,"column":134,"offset":2117},"indent":[]}},{"type":"text","value":" in order to use the ","position":{"start":{"line":30,"column":134,"offset":2117},"end":{"line":30,"column":155,"offset":2138},"indent":[]}},{"type":"html","value":"<code class=\"language-text\">warthog-link-persisted-queries</code>","position":{"start":{"line":30,"column":155,"offset":2138},"end":{"line":30,"column":187,"offset":2170},"indent":[]}},{"type":"text","value":" package.","position":{"start":{"line":30,"column":187,"offset":2170},"end":{"line":30,"column":196,"offset":2179},"indent":[]}}],"position":{"start":{"line":30,"column":3,"offset":1986},"end":{"line":30,"column":196,"offset":2179},"indent":[]}}],"position":{"start":{"line":30,"column":1,"offset":1984},"end":{"line":30,"column":196,"offset":2179},"indent":[]}},{"type":"paragraph","children":[{"type":"text","value":"Inside Warthog Server, the query registry is stored in a user-configurable cache. By default, Warthog Server uses a in-memory cache. This can be configured inside of the ","position":{"start":{"line":32,"column":1,"offset":2181},"end":{"line":32,"column":171,"offset":2351},"indent":[]}},{"type":"html","value":"<code class=\"language-text\">ApolloServer</code>","position":{"start":{"line":32,"column":171,"offset":2351},"end":{"line":32,"column":185,"offset":2365},"indent":[]}},{"type":"text","value":" constructor:","position":{"start":{"line":32,"column":185,"offset":2365},"end":{"line":32,"column":198,"offset":2378},"indent":[]}}],"position":{"start":{"line":32,"column":1,"offset":2181},"end":{"line":32,"column":198,"offset":2378},"indent":[]}},{"type":"html","lang":"js","meta":null,"value":"<div class=\"gatsby-highlight\" data-language=\"js\"><pre style=\"counter-reset: linenumber NaN\" class=\"language-js line-numbers\"><code class=\"language-js\"><span class=\"token keyword\">const</span> <span class=\"token punctuation\">{</span> MemcachedCache <span class=\"token punctuation\">}</span> <span class=\"token operator\">=</span> <span class=\"token function\">require</span><span class=\"token punctuation\">(</span><span class=\"token string\">'warthog-server-memcached'</span><span class=\"token punctuation\">)</span><span class=\"token punctuation\">;</span>\n<span class=\"token keyword\">const</span> <span class=\"token punctuation\">{</span> ApolloServer <span class=\"token punctuation\">}</span> <span class=\"token operator\">=</span> <span class=\"token function\">require</span><span class=\"token punctuation\">(</span><span class=\"token string\">'warthog-server'</span><span class=\"token punctuation\">)</span><span class=\"token punctuation\">;</span>\n\n<span class=\"token keyword\">const</span> server <span class=\"token operator\">=</span> <span class=\"token keyword\">new</span> <span class=\"token class-name\">ApolloServer</span><span class=\"token punctuation\">(</span><span class=\"token punctuation\">{</span>\n  typeDefs<span class=\"token punctuation\">,</span>\n  resolvers<span class=\"token punctuation\">,</span>\n  persistedQueries<span class=\"token punctuation\">:</span> <span class=\"token punctuation\">{</span>\n    cache<span class=\"token punctuation\">:</span> <span class=\"token keyword\">new</span> <span class=\"token class-name\">MemcachedCache</span><span class=\"token punctuation\">(</span>\n      <span class=\"token punctuation\">[</span><span class=\"token string\">'memcached-server-1'</span><span class=\"token punctuation\">,</span> <span class=\"token string\">'memcached-server-2'</span><span class=\"token punctuation\">,</span> <span class=\"token string\">'memcached-server-3'</span><span class=\"token punctuation\">]</span><span class=\"token punctuation\">,</span>\n      <span class=\"token punctuation\">{</span> retries<span class=\"token punctuation\">:</span> <span class=\"token number\">10</span><span class=\"token punctuation\">,</span> retry<span class=\"token punctuation\">:</span> <span class=\"token number\">10000</span> <span class=\"token punctuation\">}</span><span class=\"token punctuation\">,</span> <span class=\"token comment\">// Options</span>\n    <span class=\"token punctuation\">)</span><span class=\"token punctuation\">,</span>\n  <span class=\"token punctuation\">}</span><span class=\"token punctuation\">,</span>\n<span class=\"token punctuation\">}</span><span class=\"token punctuation\">)</span><span class=\"token punctuation\">;</span></code><span aria-hidden=\"true\" class=\"line-numbers-rows\" style=\"white-space: normal; width: auto; left: 0;\"><span></span><span></span><span></span><span></span><span></span><span></span><span></span><span></span><span></span><span></span><span></span><span></span><span></span></span></pre></div>","position":{"start":{"line":34,"column":1,"offset":2380},"end":{"line":48,"column":4,"offset":2756},"indent":[1,1,1,1,1,1,1,1,1,1,1,1,1,1]}},{"type":"heading","depth":3,"children":[{"type":"link","url":"#verify","title":null,"data":{"hProperties":{"aria-label":"verify permalink","class":"anchor"},"hChildren":[{"type":"raw","value":"<svg aria-hidden=\"true\" focusable=\"false\" height=\"16\" version=\"1.1\" viewBox=\"0 0 16 16\" width=\"16\"><path fill-rule=\"evenodd\" d=\"M4 9h1v1H4c-1.5 0-3-1.69-3-3.5S2.55 3 4 3h4c1.45 0 3 1.69 3 3.5 0 1.41-.91 2.72-2 3.25V8.59c.58-.45 1-1.27 1-2.09C10 5.22 8.98 4 8 4H4c-.98 0-2 1.22-2 2.5S3 9 4 9zm9-3h-1v1h1c1 0 2 1.22 2 2.5S13.98 12 13 12H9c-.98 0-2-1.22-2-2.5 0-.83.42-1.64 1-2.09V6.25c-1.09.53-2 1.84-2 3.25C6 11.31 7.55 13 9 13h4c1.45 0 3-1.69 3-3.5S14.5 6 13 6z\"></path></svg>"}]}},{"type":"text","value":"Verify","position":{"start":{"line":50,"column":5,"offset":2762},"end":{"line":50,"column":11,"offset":2768},"indent":[]}}],"position":{"start":{"line":50,"column":1,"offset":2758},"end":{"line":50,"column":11,"offset":2768},"indent":[]},"data":{"id":"verify","htmlAttributes":{"id":"verify"},"hProperties":{"id":"verify"}}},{"type":"paragraph","children":[{"type":"text","value":"Warthog Server's persisted queries configuration can be tested from the command-line. The following examples assume Warthog Server is running at ","position":{"start":{"line":52,"column":1,"offset":2770},"end":{"line":52,"column":146,"offset":2915},"indent":[]}},{"type":"html","value":"<code class=\"language-text\">localhost:4000/</code>","position":{"start":{"line":52,"column":146,"offset":2915},"end":{"line":52,"column":163,"offset":2932},"indent":[]}},{"type":"text","value":".\nThis example persists a dummy query of ","position":{"start":{"line":52,"column":163,"offset":2932},"end":{"line":53,"column":40,"offset":2973},"indent":[1]}},{"type":"html","value":"<code class=\"language-text\">{__typename}</code>","position":{"start":{"line":53,"column":40,"offset":2973},"end":{"line":53,"column":54,"offset":2987},"indent":[]}},{"type":"text","value":", using its sha256 hash: ","position":{"start":{"line":53,"column":54,"offset":2987},"end":{"line":53,"column":79,"offset":3012},"indent":[]}},{"type":"html","value":"<code class=\"language-text\">ecf4edb46db40b5132295c0291d62fb65d6759a9eedfa4d5d612dd5ec54a6b38</code>","position":{"start":{"line":53,"column":79,"offset":3012},"end":{"line":53,"column":145,"offset":3078},"indent":[]}},{"type":"text","value":".","position":{"start":{"line":53,"column":145,"offset":3078},"end":{"line":53,"column":146,"offset":3079},"indent":[]}}],"position":{"start":{"line":52,"column":1,"offset":2770},"end":{"line":53,"column":146,"offset":3079},"indent":[1]}},{"type":"list","ordered":true,"start":1,"spread":false,"children":[{"type":"listItem","spread":false,"checked":null,"children":[{"type":"paragraph","children":[{"type":"text","value":"Request a persisted query:","position":{"start":{"line":56,"column":4,"offset":3085},"end":{"line":56,"column":30,"offset":3111},"indent":[]}}],"position":{"start":{"line":56,"column":4,"offset":3085},"end":{"line":56,"column":30,"offset":3111},"indent":[]}}],"position":{"start":{"line":56,"column":1,"offset":3082},"end":{"line":56,"column":30,"offset":3111},"indent":[]}}],"position":{"start":{"line":56,"column":1,"offset":3082},"end":{"line":56,"column":30,"offset":3111},"indent":[]}},{"type":"html","lang":"bash","meta":null,"value":"<div class=\"gatsby-highlight\" data-language=\"bash\"><pre style=\"counter-reset: linenumber NaN\" class=\"language-bash line-numbers\"><code class=\"language-bash\"><span class=\"token function\">curl</span> -g <span class=\"token string\">'http://localhost:4000/?extensions={\"persistedQuery\":{\"version\":1,\"sha256Hash\":\"ecf4edb46db40b5132295c0291d62fb65d6759a9eedfa4d5d612dd5ec54a6b38\"}}'</span></code><span aria-hidden=\"true\" class=\"line-numbers-rows\" style=\"white-space: normal; width: auto; left: 0;\"><span></span></span></pre></div>","position":{"start":{"line":58,"column":1,"offset":3113},"end":{"line":60,"column":4,"offset":3281},"indent":[1,1]}},{"type":"paragraph","children":[{"type":"text","value":"   Expect a response of: ","position":{"start":{"line":62,"column":1,"offset":3283},"end":{"line":62,"column":26,"offset":3308},"indent":[]}},{"type":"html","value":"<code class=\"language-text\">{&quot;errors&quot;: [{&quot;message&quot;: &quot;PersistedQueryNotFound&quot;, &quot;extensions&quot;: {...}}]}</code>","position":{"start":{"line":62,"column":26,"offset":3308},"end":{"line":62,"column":100,"offset":3382},"indent":[]}},{"type":"text","value":".","position":{"start":{"line":62,"column":100,"offset":3382},"end":{"line":62,"column":101,"offset":3383},"indent":[]}}],"position":{"start":{"line":62,"column":1,"offset":3283},"end":{"line":62,"column":101,"offset":3383},"indent":[]}},{"type":"list","ordered":true,"start":2,"spread":false,"children":[{"type":"listItem","spread":false,"checked":null,"children":[{"type":"paragraph","children":[{"type":"text","value":"Store the query to the cache:","position":{"start":{"line":64,"column":4,"offset":3388},"end":{"line":64,"column":33,"offset":3417},"indent":[]}}],"position":{"start":{"line":64,"column":4,"offset":3388},"end":{"line":64,"column":33,"offset":3417},"indent":[]}}],"position":{"start":{"line":64,"column":1,"offset":3385},"end":{"line":64,"column":33,"offset":3417},"indent":[]}}],"position":{"start":{"line":64,"column":1,"offset":3385},"end":{"line":64,"column":33,"offset":3417},"indent":[]}},{"type":"html","lang":"bash","meta":null,"value":"<div class=\"gatsby-highlight\" data-language=\"bash\"><pre style=\"counter-reset: linenumber NaN\" class=\"language-bash line-numbers\"><code class=\"language-bash\"><span class=\"token function\">curl</span> -g <span class=\"token string\">'http://localhost:4000/?query={__typename}&amp;extensions={\"persistedQuery\":{\"version\":1,\"sha256Hash\":\"ecf4edb46db40b5132295c0291d62fb65d6759a9eedfa4d5d612dd5ec54a6b38\"}}'</span></code><span aria-hidden=\"true\" class=\"line-numbers-rows\" style=\"white-space: normal; width: auto; left: 0;\"><span></span></span></pre></div>","position":{"start":{"line":66,"column":1,"offset":3419},"end":{"line":68,"column":4,"offset":3606},"indent":[1,1]}},{"type":"paragraph","children":[{"type":"text","value":"   Expect a response of ","position":{"start":{"line":70,"column":1,"offset":3608},"end":{"line":70,"column":25,"offset":3632},"indent":[]}},{"type":"html","value":"<code class=\"language-text\">{&quot;data&quot;: {&quot;__typename&quot;: &quot;Query&quot;}}&quot;</code>","position":{"start":{"line":70,"column":25,"offset":3632},"end":{"line":70,"column":61,"offset":3668},"indent":[]}},{"type":"text","value":".","position":{"start":{"line":70,"column":61,"offset":3668},"end":{"line":70,"column":62,"offset":3669},"indent":[]}}],"position":{"start":{"line":70,"column":1,"offset":3608},"end":{"line":70,"column":62,"offset":3669},"indent":[]}},{"type":"list","ordered":true,"start":3,"spread":false,"children":[{"type":"listItem","spread":false,"checked":null,"children":[{"type":"paragraph","children":[{"type":"text","value":"Request the persisted query again:","position":{"start":{"line":72,"column":4,"offset":3674},"end":{"line":72,"column":38,"offset":3708},"indent":[]}}],"position":{"start":{"line":72,"column":4,"offset":3674},"end":{"line":72,"column":38,"offset":3708},"indent":[]}}],"position":{"start":{"line":72,"column":1,"offset":3671},"end":{"line":72,"column":38,"offset":3708},"indent":[]}}],"position":{"start":{"line":72,"column":1,"offset":3671},"end":{"line":72,"column":38,"offset":3708},"indent":[]}},{"type":"html","lang":"bash","meta":null,"value":"<div class=\"gatsby-highlight\" data-language=\"bash\"><pre style=\"counter-reset: linenumber NaN\" class=\"language-bash line-numbers\"><code class=\"language-bash\"><span class=\"token function\">curl</span> -g <span class=\"token string\">'http://localhost:4000/?extensions={\"persistedQuery\":{\"version\":1,\"sha256Hash\":\"ecf4edb46db40b5132295c0291d62fb65d6759a9eedfa4d5d612dd5ec54a6b38\"}}'</span></code><span aria-hidden=\"true\" class=\"line-numbers-rows\" style=\"white-space: normal; width: auto; left: 0;\"><span></span></span></pre></div>","position":{"start":{"line":74,"column":1,"offset":3710},"end":{"line":76,"column":4,"offset":3878},"indent":[1,1]}},{"type":"paragraph","children":[{"type":"text","value":"   Expect a response of ","position":{"start":{"line":78,"column":1,"offset":3880},"end":{"line":78,"column":25,"offset":3904},"indent":[]}},{"type":"html","value":"<code class=\"language-text\">{&quot;data&quot;: {&quot;__typename&quot;: &quot;Query&quot;}}&quot;</code>","position":{"start":{"line":78,"column":25,"offset":3904},"end":{"line":78,"column":61,"offset":3940},"indent":[]}},{"type":"text","value":", as the query string is loaded from the cache.","position":{"start":{"line":78,"column":61,"offset":3940},"end":{"line":78,"column":108,"offset":3987},"indent":[]}}],"position":{"start":{"line":78,"column":1,"offset":3880},"end":{"line":78,"column":108,"offset":3987},"indent":[]}},{"type":"heading","depth":3,"children":[{"type":"link","url":"#using-get-requests-with-apq-to-enable-cdns","title":null,"data":{"hProperties":{"aria-label":"using get requests with apq to enable cdns permalink","class":"anchor"},"hChildren":[{"type":"raw","value":"<svg aria-hidden=\"true\" focusable=\"false\" height=\"16\" version=\"1.1\" viewBox=\"0 0 16 16\" width=\"16\"><path fill-rule=\"evenodd\" d=\"M4 9h1v1H4c-1.5 0-3-1.69-3-3.5S2.55 3 4 3h4c1.45 0 3 1.69 3 3.5 0 1.41-.91 2.72-2 3.25V8.59c.58-.45 1-1.27 1-2.09C10 5.22 8.98 4 8 4H4c-.98 0-2 1.22-2 2.5S3 9 4 9zm9-3h-1v1h1c1 0 2 1.22 2 2.5S13.98 12 13 12H9c-.98 0-2-1.22-2-2.5 0-.83.42-1.64 1-2.09V6.25c-1.09.53-2 1.84-2 3.25C6 11.31 7.55 13 9 13h4c1.45 0 3-1.69 3-3.5S14.5 6 13 6z\"></path></svg>"}]}},{"type":"text","value":"Using GET requests with APQ to enable CDNs","position":{"start":{"line":80,"column":5,"offset":3993},"end":{"line":80,"column":47,"offset":4035},"indent":[]}}],"position":{"start":{"line":80,"column":1,"offset":3989},"end":{"line":80,"column":47,"offset":4035},"indent":[]},"data":{"id":"using-get-requests-with-apq-to-enable-cdns","htmlAttributes":{"id":"using-get-requests-with-apq-to-enable-cdns"},"hProperties":{"id":"using-get-requests-with-apq-to-enable-cdns"}}},{"type":"paragraph","children":[{"type":"text","value":"A great application for APQ is running Warthog Server behind a CDN. Many CDNs only cache GET requests, but many GraphQL queries are too long to fit comfortably in a cacheable GET request.  When the APQ link is created with ","position":{"start":{"line":82,"column":1,"offset":4037},"end":{"line":82,"column":224,"offset":4260},"indent":[]}},{"type":"html","value":"<code class=\"language-text\">createPersistedQueryLink({useGETForHashedQueries: true})</code>","position":{"start":{"line":82,"column":224,"offset":4260},"end":{"line":82,"column":282,"offset":4318},"indent":[]}},{"type":"text","value":", Warthog Client automatically sends the short hashed queries as GET requests allowing a CDN to serve those request. For full-length queries and for all mutations, Warthog Client will continue to use POST requests.","position":{"start":{"line":82,"column":282,"offset":4318},"end":{"line":82,"column":496,"offset":4532},"indent":[]}}],"position":{"start":{"line":82,"column":1,"offset":4037},"end":{"line":82,"column":496,"offset":4532},"indent":[]}},{"type":"heading","depth":3,"children":[{"type":"link","url":"#how-it-works","title":null,"data":{"hProperties":{"aria-label":"how it works permalink","class":"anchor"},"hChildren":[{"type":"raw","value":"<svg aria-hidden=\"true\" focusable=\"false\" height=\"16\" version=\"1.1\" viewBox=\"0 0 16 16\" width=\"16\"><path fill-rule=\"evenodd\" d=\"M4 9h1v1H4c-1.5 0-3-1.69-3-3.5S2.55 3 4 3h4c1.45 0 3 1.69 3 3.5 0 1.41-.91 2.72-2 3.25V8.59c.58-.45 1-1.27 1-2.09C10 5.22 8.98 4 8 4H4c-.98 0-2 1.22-2 2.5S3 9 4 9zm9-3h-1v1h1c1 0 2 1.22 2 2.5S13.98 12 13 12H9c-.98 0-2-1.22-2-2.5 0-.83.42-1.64 1-2.09V6.25c-1.09.53-2 1.84-2 3.25C6 11.31 7.55 13 9 13h4c1.45 0 3-1.69 3-3.5S14.5 6 13 6z\"></path></svg>"}]}},{"type":"text","value":"How it works","position":{"start":{"line":84,"column":5,"offset":4538},"end":{"line":84,"column":17,"offset":4550},"indent":[]}}],"position":{"start":{"line":84,"column":1,"offset":4534},"end":{"line":84,"column":17,"offset":4550},"indent":[]},"data":{"id":"how-it-works","htmlAttributes":{"id":"how-it-works"},"hProperties":{"id":"how-it-works"}}},{"type":"paragraph","children":[{"type":"text","value":"The mechanism is based on a lightweight protocol extension between Warthog Client and Warthog Server. It works as follows:","position":{"start":{"line":86,"column":1,"offset":4552},"end":{"line":86,"column":123,"offset":4674},"indent":[]}}],"position":{"start":{"line":86,"column":1,"offset":4552},"end":{"line":86,"column":123,"offset":4674},"indent":[]}},{"type":"list","ordered":false,"start":null,"spread":true,"children":[{"type":"listItem","spread":false,"checked":null,"children":[{"type":"paragraph","children":[{"type":"text","value":"When the client makes a query, it will optimistically send a short (64-byte) cryptographic hash instead of the full query text.","position":{"start":{"line":88,"column":3,"offset":4678},"end":{"line":88,"column":130,"offset":4805},"indent":[]}}],"position":{"start":{"line":88,"column":3,"offset":4678},"end":{"line":88,"column":130,"offset":4805},"indent":[]}}],"position":{"start":{"line":88,"column":1,"offset":4676},"end":{"line":88,"column":130,"offset":4805},"indent":[]}},{"type":"listItem","spread":true,"checked":null,"children":[{"type":"paragraph","children":[{"type":"strong","children":[{"type":"text","value":"Optimized Path:","position":{"start":{"line":89,"column":5,"offset":4810},"end":{"line":89,"column":20,"offset":4825},"indent":[]}}],"position":{"start":{"line":89,"column":3,"offset":4808},"end":{"line":89,"column":22,"offset":4827},"indent":[]}},{"type":"text","value":" If a request containing a persisted query hash is detected, Warthog Server will look it up to find a corresponding query in its registry. Upon finding a match, Warthog Server will expand the request with the full text of the query and execute it.","position":{"start":{"line":89,"column":22,"offset":4827},"end":{"line":89,"column":269,"offset":5074},"indent":[]}}],"position":{"start":{"line":89,"column":3,"offset":4808},"end":{"line":89,"column":269,"offset":5074},"indent":[]}},{"type":"html","value":"<img src=\"/persistedQueries.optPath-98cb0f1ed777fbd3fb0d0701e41d5dee.png\" width=\"80%\" style=\"margin: 5%\" alt=\"Optimized Path\">","position":{"start":{"line":91,"column":3,"offset":5078},"end":{"line":91,"column":105,"offset":5180},"indent":[]}}],"position":{"start":{"line":89,"column":1,"offset":4806},"end":{"line":92,"column":1,"offset":5181},"indent":[1,1,1]}},{"type":"listItem","spread":true,"checked":null,"children":[{"type":"paragraph","children":[{"type":"strong","children":[{"type":"text","value":"New Query Path:","position":{"start":{"line":93,"column":5,"offset":5186},"end":{"line":93,"column":20,"offset":5201},"indent":[]}}],"position":{"start":{"line":93,"column":3,"offset":5184},"end":{"line":93,"column":22,"offset":5203},"indent":[]}},{"type":"text","value":" In the unlikely event that the query is not already in the Warthog Server registry (this only happens the very first time that Warthog Server sees a query), it will ask the client to resend the request using the full text of the query. At that point Warthog Server will store the query / hash mapping in the registry for all subsequent requests to benefit from.","position":{"start":{"line":93,"column":22,"offset":5203},"end":{"line":93,"column":384,"offset":5565},"indent":[]}}],"position":{"start":{"line":93,"column":3,"offset":5184},"end":{"line":93,"column":384,"offset":5565},"indent":[]}},{"type":"html","value":"<img src=\"/persistedQueries.newPath-d500b543a6ad2a7d64ed7f190d40bd8c.png\" width=\"80%\" style=\"margin: 5%;\" alt=\"New Query Path\">","position":{"start":{"line":95,"column":3,"offset":5569},"end":{"line":95,"column":106,"offset":5672},"indent":[]}}],"position":{"start":{"line":93,"column":1,"offset":5182},"end":{"line":95,"column":106,"offset":5672},"indent":[1,1]}}],"position":{"start":{"line":88,"column":1,"offset":4676},"end":{"line":95,"column":106,"offset":5672},"indent":[1,1,1,1,1,1,1]}},{"type":"heading","depth":2,"children":[{"type":"link","url":"#cdn-integration","title":null,"data":{"hProperties":{"aria-label":"cdn integration permalink","class":"anchor"},"hChildren":[{"type":"raw","value":"<svg aria-hidden=\"true\" focusable=\"false\" height=\"16\" version=\"1.1\" viewBox=\"0 0 16 16\" width=\"16\"><path fill-rule=\"evenodd\" d=\"M4 9h1v1H4c-1.5 0-3-1.69-3-3.5S2.55 3 4 3h4c1.45 0 3 1.69 3 3.5 0 1.41-.91 2.72-2 3.25V8.59c.58-.45 1-1.27 1-2.09C10 5.22 8.98 4 8 4H4c-.98 0-2 1.22-2 2.5S3 9 4 9zm9-3h-1v1h1c1 0 2 1.22 2 2.5S13.98 12 13 12H9c-.98 0-2-1.22-2-2.5 0-.83.42-1.64 1-2.09V6.25c-1.09.53-2 1.84-2 3.25C6 11.31 7.55 13 9 13h4c1.45 0 3-1.69 3-3.5S14.5 6 13 6z\"></path></svg>"}]}},{"type":"text","value":"CDN Integration","position":{"start":{"line":97,"column":4,"offset":5677},"end":{"line":97,"column":19,"offset":5692},"indent":[]}}],"position":{"start":{"line":97,"column":1,"offset":5674},"end":{"line":97,"column":19,"offset":5692},"indent":[]},"data":{"id":"cdn-integration","htmlAttributes":{"id":"cdn-integration"},"hProperties":{"id":"cdn-integration"}}},{"type":"paragraph","children":[{"type":"text","value":"Content Delivery Networks (CDNs) such as ","position":{"start":{"line":99,"column":1,"offset":5694},"end":{"line":99,"column":42,"offset":5735},"indent":[]}},{"type":"link","title":null,"url":"https://fly.io","children":[{"type":"text","value":"fly.io","position":{"start":{"line":99,"column":43,"offset":5736},"end":{"line":99,"column":49,"offset":5742},"indent":[]}}],"position":{"start":{"line":99,"column":42,"offset":5735},"end":{"line":99,"column":66,"offset":5759},"indent":[]}},{"type":"text","value":", ","position":{"start":{"line":99,"column":66,"offset":5759},"end":{"line":99,"column":68,"offset":5761},"indent":[]}},{"type":"link","title":null,"url":"https://www.cloudflare.com/","children":[{"type":"text","value":"Cloudflare","position":{"start":{"line":99,"column":69,"offset":5762},"end":{"line":99,"column":79,"offset":5772},"indent":[]}}],"position":{"start":{"line":99,"column":68,"offset":5761},"end":{"line":99,"column":109,"offset":5802},"indent":[]}},{"type":"text","value":", ","position":{"start":{"line":99,"column":109,"offset":5802},"end":{"line":99,"column":111,"offset":5804},"indent":[]}},{"type":"link","title":null,"url":"https://www.akamai.com/","children":[{"type":"text","value":"Akamai","position":{"start":{"line":99,"column":112,"offset":5805},"end":{"line":99,"column":118,"offset":5811},"indent":[]}}],"position":{"start":{"line":99,"column":111,"offset":5804},"end":{"line":99,"column":144,"offset":5837},"indent":[]}},{"type":"text","value":" or ","position":{"start":{"line":99,"column":144,"offset":5837},"end":{"line":99,"column":148,"offset":5841},"indent":[]}},{"type":"link","title":null,"url":"https://www.fastly.com/","children":[{"type":"text","value":"Fastly","position":{"start":{"line":99,"column":149,"offset":5842},"end":{"line":99,"column":155,"offset":5848},"indent":[]}}],"position":{"start":{"line":99,"column":148,"offset":5841},"end":{"line":99,"column":181,"offset":5874},"indent":[]}},{"type":"text","value":" allow content caching close to clients, delivering data with low latency from a nearby server. Warthog Server makes it straightforward to use CDNs with GraphQL queries to cache full responses while still executing more dynamic queries.","position":{"start":{"line":99,"column":181,"offset":5874},"end":{"line":99,"column":417,"offset":6110},"indent":[]}}],"position":{"start":{"line":99,"column":1,"offset":5694},"end":{"line":99,"column":417,"offset":6110},"indent":[]}},{"type":"paragraph","children":[{"type":"text","value":"To use Warthog Server behind a CDN, we define which GraphQL responses the CDN is allowed to cache. On the client, we set up ","position":{"start":{"line":101,"column":1,"offset":6112},"end":{"line":101,"column":125,"offset":6236},"indent":[]}},{"type":"link","title":null,"url":"#automatic-persisted-queries","children":[{"type":"text","value":"automatic persisted queries","position":{"start":{"line":101,"column":126,"offset":6237},"end":{"line":101,"column":153,"offset":6264},"indent":[]}}],"position":{"start":{"line":101,"column":125,"offset":6236},"end":{"line":101,"column":184,"offset":6295},"indent":[]}},{"type":"text","value":" to ensure that GraphQL requests are in a format that a CDN can understand.","position":{"start":{"line":101,"column":184,"offset":6295},"end":{"line":101,"column":259,"offset":6370},"indent":[]}}],"position":{"start":{"line":101,"column":1,"offset":6112},"end":{"line":101,"column":259,"offset":6370},"indent":[]}},{"type":"heading","depth":3,"children":[{"type":"link","url":"#step-1-add-cache-hints-to-the-graphql-schema","title":null,"data":{"hProperties":{"aria-label":"step 1 add cache hints to the graphql schema permalink","class":"anchor"},"hChildren":[{"type":"raw","value":"<svg aria-hidden=\"true\" focusable=\"false\" height=\"16\" version=\"1.1\" viewBox=\"0 0 16 16\" width=\"16\"><path fill-rule=\"evenodd\" d=\"M4 9h1v1H4c-1.5 0-3-1.69-3-3.5S2.55 3 4 3h4c1.45 0 3 1.69 3 3.5 0 1.41-.91 2.72-2 3.25V8.59c.58-.45 1-1.27 1-2.09C10 5.22 8.98 4 8 4H4c-.98 0-2 1.22-2 2.5S3 9 4 9zm9-3h-1v1h1c1 0 2 1.22 2 2.5S13.98 12 13 12H9c-.98 0-2-1.22-2-2.5 0-.83.42-1.64 1-2.09V6.25c-1.09.53-2 1.84-2 3.25C6 11.31 7.55 13 9 13h4c1.45 0 3-1.69 3-3.5S14.5 6 13 6z\"></path></svg>"}]}},{"type":"text","value":"Step 1: Add cache hints to the GraphQL schema","position":{"start":{"line":103,"column":5,"offset":6376},"end":{"line":103,"column":50,"offset":6421},"indent":[]}}],"position":{"start":{"line":103,"column":1,"offset":6372},"end":{"line":103,"column":50,"offset":6421},"indent":[]},"data":{"id":"step-1-add-cache-hints-to-the-graphql-schema","htmlAttributes":{"id":"step-1-add-cache-hints-to-the-graphql-schema"},"hProperties":{"id":"step-1-add-cache-hints-to-the-graphql-schema"}}},{"type":"paragraph","children":[{"type":"text","value":"Add cache hints as ","position":{"start":{"line":105,"column":1,"offset":6423},"end":{"line":105,"column":20,"offset":6442},"indent":[]}},{"type":"link","title":null,"url":"https://www.warthog.dev/docs/warthog-server/features/caching#defining-cache-hints","children":[{"type":"text","value":"directives","position":{"start":{"line":105,"column":21,"offset":6443},"end":{"line":105,"column":31,"offset":6453},"indent":[]}}],"position":{"start":{"line":105,"column":20,"offset":6442},"end":{"line":105,"column":115,"offset":6537},"indent":[]}},{"type":"text","value":" to GraphQL schema so that Warthog Server knows which fields and types are cacheable and for how long. For example, this schema indicates that all fields that return an ","position":{"start":{"line":105,"column":115,"offset":6537},"end":{"line":105,"column":284,"offset":6706},"indent":[]}},{"type":"html","value":"<code class=\"language-text\">Author</code>","position":{"start":{"line":105,"column":284,"offset":6706},"end":{"line":105,"column":292,"offset":6714},"indent":[]}},{"type":"text","value":" should be cached for 60 seconds, and that the ","position":{"start":{"line":105,"column":292,"offset":6714},"end":{"line":105,"column":339,"offset":6761},"indent":[]}},{"type":"html","value":"<code class=\"language-text\">posts</code>","position":{"start":{"line":105,"column":339,"offset":6761},"end":{"line":105,"column":346,"offset":6768},"indent":[]}},{"type":"text","value":" field should itself be cached for 180 seconds:","position":{"start":{"line":105,"column":346,"offset":6768},"end":{"line":105,"column":393,"offset":6815},"indent":[]}}],"position":{"start":{"line":105,"column":1,"offset":6423},"end":{"line":105,"column":393,"offset":6815},"indent":[]}},{"type":"html","lang":"graphql","meta":null,"value":"<div class=\"gatsby-highlight\" data-language=\"graphql\"><pre style=\"counter-reset: linenumber NaN\" class=\"language-graphql line-numbers\"><code class=\"language-graphql\"><span class=\"token keyword\">type</span> <span class=\"token class-name\">Author</span> <span class=\"token directive function\">@cacheControl</span><span class=\"token punctuation\">(</span><span class=\"token attr-name\">maxAge</span><span class=\"token punctuation\">:</span> <span class=\"token number\">60</span><span class=\"token punctuation\">)</span> <span class=\"token punctuation\">{</span>\n  <span class=\"token attr-name\">id</span><span class=\"token punctuation\">:</span> Int\n  <span class=\"token attr-name\">firstName</span><span class=\"token punctuation\">:</span> String\n  <span class=\"token attr-name\">lastName</span><span class=\"token punctuation\">:</span> String\n  <span class=\"token attr-name\">posts</span><span class=\"token punctuation\">:</span> <span class=\"token punctuation\">[</span>Post<span class=\"token punctuation\">]</span> <span class=\"token directive function\">@cacheControl</span><span class=\"token punctuation\">(</span><span class=\"token attr-name\">maxAge</span><span class=\"token punctuation\">:</span> <span class=\"token number\">180</span><span class=\"token punctuation\">)</span>\n<span class=\"token punctuation\">}</span></code><span aria-hidden=\"true\" class=\"line-numbers-rows\" style=\"white-space: normal; width: auto; left: 0;\"><span></span><span></span><span></span><span></span><span></span><span></span></span></pre></div>","position":{"start":{"line":107,"column":1,"offset":6817},"end":{"line":114,"column":4,"offset":6965},"indent":[1,1,1,1,1,1,1]}},{"type":"paragraph","children":[{"type":"text","value":"See ","position":{"start":{"line":116,"column":1,"offset":6967},"end":{"line":116,"column":5,"offset":6971},"indent":[]}},{"type":"link","title":null,"url":"https://github.com/goldcaddy77/warthog-cache-control-js#add-cache-hints-to-your-schema","children":[{"type":"text","value":"the cache control documentation","position":{"start":{"line":116,"column":6,"offset":6972},"end":{"line":116,"column":37,"offset":7003},"indent":[]}}],"position":{"start":{"line":116,"column":5,"offset":6971},"end":{"line":116,"column":126,"offset":7092},"indent":[]}},{"type":"text","value":" for more details, including how to specify hints dynamically inside resolvers, how to set a default ","position":{"start":{"line":116,"column":126,"offset":7092},"end":{"line":116,"column":227,"offset":7193},"indent":[]}},{"type":"html","value":"<code class=\"language-text\">maxAge</code>","position":{"start":{"line":116,"column":227,"offset":7193},"end":{"line":116,"column":235,"offset":7201},"indent":[]}},{"type":"text","value":" for all fields, and how to specify that a field should be cached for specific users only (in which case CDNs should ignore it). For example, to set a default max age other than ","position":{"start":{"line":116,"column":235,"offset":7201},"end":{"line":116,"column":413,"offset":7379},"indent":[]}},{"type":"html","value":"<code class=\"language-text\">0</code>","position":{"start":{"line":116,"column":413,"offset":7379},"end":{"line":116,"column":416,"offset":7382},"indent":[]}},{"type":"text","value":" modify the Warthog Server constructor to include ","position":{"start":{"line":116,"column":416,"offset":7382},"end":{"line":116,"column":466,"offset":7432},"indent":[]}},{"type":"html","value":"<code class=\"language-text\">cacheControl</code>","position":{"start":{"line":116,"column":466,"offset":7432},"end":{"line":116,"column":480,"offset":7446},"indent":[]}},{"type":"text","value":":","position":{"start":{"line":116,"column":480,"offset":7446},"end":{"line":116,"column":481,"offset":7447},"indent":[]}}],"position":{"start":{"line":116,"column":1,"offset":6967},"end":{"line":116,"column":481,"offset":7447},"indent":[]}},{"type":"html","lang":"js","meta":null,"value":"<div class=\"gatsby-highlight\" data-language=\"js\"><pre style=\"counter-reset: linenumber NaN\" class=\"language-js line-numbers\"><code class=\"language-js\"><span class=\"token keyword\">const</span> server <span class=\"token operator\">=</span> <span class=\"token keyword\">new</span> <span class=\"token class-name\">ApolloServer</span><span class=\"token punctuation\">(</span><span class=\"token punctuation\">{</span>\n  typeDefs<span class=\"token punctuation\">,</span>\n  resolvers<span class=\"token punctuation\">,</span>\n  <span class=\"token comment\">// The max age is calculated in seconds</span>\n  cacheControl<span class=\"token punctuation\">:</span> <span class=\"token punctuation\">{</span> defaultMaxAge<span class=\"token punctuation\">:</span> <span class=\"token number\">5</span> <span class=\"token punctuation\">}</span><span class=\"token punctuation\">,</span>\n<span class=\"token punctuation\">}</span><span class=\"token punctuation\">)</span><span class=\"token punctuation\">;</span></code><span aria-hidden=\"true\" class=\"line-numbers-rows\" style=\"white-space: normal; width: auto; left: 0;\"><span></span><span></span><span></span><span></span><span></span><span></span></span></pre></div>","position":{"start":{"line":118,"column":1,"offset":7449},"end":{"line":125,"column":4,"offset":7601},"indent":[1,1,1,1,1,1,1]}},{"type":"paragraph","children":[{"type":"text","value":"After this step, Warthog Server will serve the HTTP ","position":{"start":{"line":127,"column":1,"offset":7603},"end":{"line":127,"column":53,"offset":7655},"indent":[]}},{"type":"html","value":"<code class=\"language-text\">Cache-Control</code>","position":{"start":{"line":127,"column":53,"offset":7655},"end":{"line":127,"column":68,"offset":7670},"indent":[]}},{"type":"text","value":" header on fully cacheable responses, so that any CDN in front of Warthog Server will know which responses can be cached and for how long! A \"fully cacheable\" response contains only data with non-zero ","position":{"start":{"line":127,"column":68,"offset":7670},"end":{"line":127,"column":269,"offset":7871},"indent":[]}},{"type":"html","value":"<code class=\"language-text\">maxAge</code>","position":{"start":{"line":127,"column":269,"offset":7871},"end":{"line":127,"column":277,"offset":7879},"indent":[]}},{"type":"text","value":"; the header will refer to the minimum ","position":{"start":{"line":127,"column":277,"offset":7879},"end":{"line":127,"column":316,"offset":7918},"indent":[]}},{"type":"html","value":"<code class=\"language-text\">maxAge</code>","position":{"start":{"line":127,"column":316,"offset":7918},"end":{"line":127,"column":324,"offset":7926},"indent":[]}},{"type":"text","value":" value across the whole response, and it will be ","position":{"start":{"line":127,"column":324,"offset":7926},"end":{"line":127,"column":373,"offset":7975},"indent":[]}},{"type":"html","value":"<code class=\"language-text\">public</code>","position":{"start":{"line":127,"column":373,"offset":7975},"end":{"line":127,"column":381,"offset":7983},"indent":[]}},{"type":"text","value":" unless some of the data is tagged ","position":{"start":{"line":127,"column":381,"offset":7983},"end":{"line":127,"column":416,"offset":8018},"indent":[]}},{"type":"html","value":"<code class=\"language-text\">scope: PRIVATE</code>","position":{"start":{"line":127,"column":416,"offset":8018},"end":{"line":127,"column":432,"offset":8034},"indent":[]}},{"type":"text","value":". To observe this header, use any browser's network tab in its dev tools.","position":{"start":{"line":127,"column":432,"offset":8034},"end":{"line":127,"column":505,"offset":8107},"indent":[]}}],"position":{"start":{"line":127,"column":1,"offset":7603},"end":{"line":127,"column":505,"offset":8107},"indent":[]}},{"type":"heading","depth":3,"children":[{"type":"link","url":"#step-2-enable-automatic-persisted-queries","title":null,"data":{"hProperties":{"aria-label":"step 2 enable automatic persisted queries permalink","class":"anchor"},"hChildren":[{"type":"raw","value":"<svg aria-hidden=\"true\" focusable=\"false\" height=\"16\" version=\"1.1\" viewBox=\"0 0 16 16\" width=\"16\"><path fill-rule=\"evenodd\" d=\"M4 9h1v1H4c-1.5 0-3-1.69-3-3.5S2.55 3 4 3h4c1.45 0 3 1.69 3 3.5 0 1.41-.91 2.72-2 3.25V8.59c.58-.45 1-1.27 1-2.09C10 5.22 8.98 4 8 4H4c-.98 0-2 1.22-2 2.5S3 9 4 9zm9-3h-1v1h1c1 0 2 1.22 2 2.5S13.98 12 13 12H9c-.98 0-2-1.22-2-2.5 0-.83.42-1.64 1-2.09V6.25c-1.09.53-2 1.84-2 3.25C6 11.31 7.55 13 9 13h4c1.45 0 3-1.69 3-3.5S14.5 6 13 6z\"></path></svg>"}]}},{"type":"text","value":"Step 2: Enable automatic persisted queries","position":{"start":{"line":129,"column":5,"offset":8113},"end":{"line":129,"column":47,"offset":8155},"indent":[]}}],"position":{"start":{"line":129,"column":1,"offset":8109},"end":{"line":129,"column":47,"offset":8155},"indent":[]},"data":{"id":"step-2-enable-automatic-persisted-queries","htmlAttributes":{"id":"step-2-enable-automatic-persisted-queries"},"hProperties":{"id":"step-2-enable-automatic-persisted-queries"}}},{"type":"paragraph","children":[{"type":"text","value":"Often, GraphQL requests are big POST requests and most CDNs will only cache GET requests. Additionally, GET requests generally work best when the URL has a bounded size. Enabling automatic persisted queries means that short hashes are sent over the wire instead of full queries, and Warthog Client can be configured to use GET requests for those hashed queries.","position":{"start":{"line":131,"column":1,"offset":8157},"end":{"line":131,"column":362,"offset":8518},"indent":[]}}],"position":{"start":{"line":131,"column":1,"offset":8157},"end":{"line":131,"column":362,"offset":8518},"indent":[]}},{"type":"paragraph","children":[{"type":"text","value":"To do this, update the ","position":{"start":{"line":133,"column":1,"offset":8520},"end":{"line":133,"column":24,"offset":8543},"indent":[]}},{"type":"strong","children":[{"type":"text","value":"client","position":{"start":{"line":133,"column":26,"offset":8545},"end":{"line":133,"column":32,"offset":8551},"indent":[]}}],"position":{"start":{"line":133,"column":24,"offset":8543},"end":{"line":133,"column":34,"offset":8553},"indent":[]}},{"type":"text","value":" code. First, add the package:","position":{"start":{"line":133,"column":34,"offset":8553},"end":{"line":133,"column":64,"offset":8583},"indent":[]}}],"position":{"start":{"line":133,"column":1,"offset":8520},"end":{"line":133,"column":64,"offset":8583},"indent":[]}},{"type":"html","lang":null,"meta":null,"value":"<div class=\"gatsby-highlight\" data-language=\"text\"><pre style=\"counter-reset: linenumber NaN\" class=\"language-text line-numbers\"><code class=\"language-text\">npm install warthog-link-persisted-queries</code><span aria-hidden=\"true\" class=\"line-numbers-rows\" style=\"white-space: normal; width: auto; left: 0;\"><span></span></span></pre></div>","position":{"start":{"line":135,"column":1,"offset":8585},"end":{"line":137,"column":4,"offset":8635},"indent":[1,1]}},{"type":"paragraph","children":[{"type":"text","value":"Then, add the persisted queries link to the Warthog Client constructor before the HTTP link:","position":{"start":{"line":139,"column":1,"offset":8637},"end":{"line":139,"column":93,"offset":8729},"indent":[]}}],"position":{"start":{"line":139,"column":1,"offset":8637},"end":{"line":139,"column":93,"offset":8729},"indent":[]}},{"type":"html","lang":"js","meta":null,"value":"<div class=\"gatsby-highlight\" data-language=\"js\"><pre style=\"counter-reset: linenumber NaN\" class=\"language-js line-numbers\"><code class=\"language-js\"><span class=\"token keyword\">import</span> <span class=\"token punctuation\">{</span> createPersistedQueryLink <span class=\"token punctuation\">}</span> <span class=\"token keyword\">from</span> <span class=\"token string\">\"warthog-link-persisted-queries\"</span><span class=\"token punctuation\">;</span>\n<span class=\"token keyword\">import</span> <span class=\"token punctuation\">{</span> createHttpLink <span class=\"token punctuation\">}</span> <span class=\"token keyword\">from</span> <span class=\"token string\">\"warthog-link-http\"</span><span class=\"token punctuation\">;</span>\n<span class=\"token keyword\">import</span> <span class=\"token punctuation\">{</span> InMemoryCache <span class=\"token punctuation\">}</span> <span class=\"token keyword\">from</span> <span class=\"token string\">\"warthog-cache-inmemory\"</span><span class=\"token punctuation\">;</span>\n<span class=\"token keyword\">import</span> <span class=\"token punctuation\">{</span> ApolloLink <span class=\"token punctuation\">}</span> <span class=\"token keyword\">from</span> <span class=\"token string\">\"warthog-link\"</span><span class=\"token punctuation\">;</span>\n<span class=\"token keyword\">import</span> ApolloClient <span class=\"token keyword\">from</span> <span class=\"token string\">\"warthog-client\"</span><span class=\"token punctuation\">;</span>\n\nApolloLink<span class=\"token punctuation\">.</span><span class=\"token function\">from</span><span class=\"token punctuation\">(</span><span class=\"token punctuation\">[</span>\n  <span class=\"token function\">createPersistedQueryLink</span><span class=\"token punctuation\">(</span><span class=\"token punctuation\">{</span> useGETForHashedQueries<span class=\"token punctuation\">:</span> <span class=\"token boolean\">true</span> <span class=\"token punctuation\">}</span><span class=\"token punctuation\">)</span><span class=\"token punctuation\">,</span>\n  <span class=\"token function\">createHttpLink</span><span class=\"token punctuation\">(</span><span class=\"token punctuation\">{</span> uri<span class=\"token punctuation\">:</span> <span class=\"token string\">\"/graphql\"</span> <span class=\"token punctuation\">}</span><span class=\"token punctuation\">)</span>\n<span class=\"token punctuation\">]</span><span class=\"token punctuation\">)</span><span class=\"token punctuation\">;</span>\n\n<span class=\"token keyword\">const</span> client <span class=\"token operator\">=</span> <span class=\"token keyword\">new</span> <span class=\"token class-name\">ApolloClient</span><span class=\"token punctuation\">(</span><span class=\"token punctuation\">{</span>\n  cache<span class=\"token punctuation\">:</span> <span class=\"token keyword\">new</span> <span class=\"token class-name\">InMemoryCache</span><span class=\"token punctuation\">(</span><span class=\"token punctuation\">)</span><span class=\"token punctuation\">,</span>\n  link<span class=\"token punctuation\">:</span> link\n<span class=\"token punctuation\">}</span><span class=\"token punctuation\">)</span><span class=\"token punctuation\">;</span></code><span aria-hidden=\"true\" class=\"line-numbers-rows\" style=\"white-space: normal; width: auto; left: 0;\"><span></span><span></span><span></span><span></span><span></span><span></span><span></span><span></span><span></span><span></span><span></span><span></span><span></span><span></span><span></span></span></pre></div>","position":{"start":{"line":141,"column":1,"offset":8731},"end":{"line":157,"column":4,"offset":9214},"indent":[1,1,1,1,1,1,1,1,1,1,1,1,1,1,1,1]}},{"type":"paragraph","children":[{"type":"text","value":"Make sure to include ","position":{"start":{"line":159,"column":1,"offset":9216},"end":{"line":159,"column":22,"offset":9237},"indent":[]}},{"type":"html","value":"<code class=\"language-text\">useGETForHashedQueries: true</code>","position":{"start":{"line":159,"column":22,"offset":9237},"end":{"line":159,"column":52,"offset":9267},"indent":[]}},{"type":"text","value":". Note that the client will still use POSTs for mutations, because it's generally best to avoid GETs for non-idempotent requests.","position":{"start":{"line":159,"column":52,"offset":9267},"end":{"line":159,"column":181,"offset":9396},"indent":[]}}],"position":{"start":{"line":159,"column":1,"offset":9216},"end":{"line":159,"column":181,"offset":9396},"indent":[]}},{"type":"paragraph","children":[{"type":"text","value":"If configured correctly, browser's dev tools should verify that queries are now sent as GET requests, and receive appropriate ","position":{"start":{"line":161,"column":1,"offset":9398},"end":{"line":161,"column":127,"offset":9524},"indent":[]}},{"type":"html","value":"<code class=\"language-text\">Cache-Control</code>","position":{"start":{"line":161,"column":127,"offset":9524},"end":{"line":161,"column":142,"offset":9539},"indent":[]}},{"type":"text","value":" response headers.","position":{"start":{"line":161,"column":142,"offset":9539},"end":{"line":161,"column":160,"offset":9557},"indent":[]}}],"position":{"start":{"line":161,"column":1,"offset":9398},"end":{"line":161,"column":160,"offset":9557},"indent":[]}},{"type":"heading","depth":3,"children":[{"type":"link","url":"#step-3-set-up-a-cdn","title":null,"data":{"hProperties":{"aria-label":"step 3 set up a cdn permalink","class":"anchor"},"hChildren":[{"type":"raw","value":"<svg aria-hidden=\"true\" focusable=\"false\" height=\"16\" version=\"1.1\" viewBox=\"0 0 16 16\" width=\"16\"><path fill-rule=\"evenodd\" d=\"M4 9h1v1H4c-1.5 0-3-1.69-3-3.5S2.55 3 4 3h4c1.45 0 3 1.69 3 3.5 0 1.41-.91 2.72-2 3.25V8.59c.58-.45 1-1.27 1-2.09C10 5.22 8.98 4 8 4H4c-.98 0-2 1.22-2 2.5S3 9 4 9zm9-3h-1v1h1c1 0 2 1.22 2 2.5S13.98 12 13 12H9c-.98 0-2-1.22-2-2.5 0-.83.42-1.64 1-2.09V6.25c-1.09.53-2 1.84-2 3.25C6 11.31 7.55 13 9 13h4c1.45 0 3-1.69 3-3.5S14.5 6 13 6z\"></path></svg>"}]}},{"type":"text","value":"Step 3: Set up a CDN!","position":{"start":{"line":163,"column":5,"offset":9563},"end":{"line":163,"column":26,"offset":9584},"indent":[]}}],"position":{"start":{"line":163,"column":1,"offset":9559},"end":{"line":163,"column":26,"offset":9584},"indent":[]},"data":{"id":"step-3-set-up-a-cdn","htmlAttributes":{"id":"step-3-set-up-a-cdn"},"hProperties":{"id":"step-3-set-up-a-cdn"}}},{"type":"paragraph","children":[{"type":"text","value":"How exactly this works depends on exactly which CDN you chose. Configure your CDN to send requests to Warthog Server. Some CDNs may need to be specially configured to honor origin Cache-Control headers; for example, here is ","position":{"start":{"line":165,"column":1,"offset":9586},"end":{"line":165,"column":225,"offset":9810},"indent":[]}},{"type":"link","title":null,"url":"https://learn.akamai.com/en-us/webhelp/ion/oca/GUID-57C31126-F745-4FFB-AA92-6A5AAC36A8DA.html","children":[{"type":"text","value":"Akamai's documentation on that setting","position":{"start":{"line":165,"column":226,"offset":9811},"end":{"line":165,"column":264,"offset":9849},"indent":[]}}],"position":{"start":{"line":165,"column":225,"offset":9810},"end":{"line":165,"column":360,"offset":9945},"indent":[]}},{"type":"text","value":". If all is well, cacheable queries should now be saved by the CDN!","position":{"start":{"line":165,"column":360,"offset":9945},"end":{"line":165,"column":427,"offset":10012},"indent":[]}}],"position":{"start":{"line":165,"column":1,"offset":9586},"end":{"line":165,"column":427,"offset":10012},"indent":[]}},{"type":"blockquote","children":[{"type":"paragraph","children":[{"type":"text","value":"Note that requests served directly by a CDN will not show up in the Engine dashboard.","position":{"start":{"line":167,"column":3,"offset":10016},"end":{"line":167,"column":88,"offset":10101},"indent":[]}}],"position":{"start":{"line":167,"column":3,"offset":10016},"end":{"line":167,"column":88,"offset":10101},"indent":[]}}],"position":{"start":{"line":167,"column":1,"offset":10014},"end":{"line":167,"column":88,"offset":10101},"indent":[]}}],"position":{"start":{"line":1,"column":1,"offset":0},"end":{"line":168,"column":1,"offset":10102}}}}