{"expireTime":9007200819376317000,"key":"transformer-remark-markdown-ast-29461ced126445576a7827494b41870a-gatsby-remark-autolink-headersgatsby-remark-copy-linked-filesgatsby-remark-prismjsgatsby-remark-check-links-","val":{"type":"root","children":[{"type":"paragraph","children":[{"type":"text","value":"One of our fundamental beliefs is that our Warthog workflows should hook into and enhance the workflows you're already using. As such, we've built a number of integrations into third-party services that are common in the developer world:","position":{"start":{"line":2,"column":1,"offset":1},"end":{"line":2,"column":238,"offset":238},"indent":[]}}],"position":{"start":{"line":2,"column":1,"offset":1},"end":{"line":2,"column":238,"offset":238},"indent":[]}},{"type":"list","ordered":true,"start":1,"spread":false,"children":[{"type":"listItem","spread":false,"checked":null,"children":[{"type":"paragraph","children":[{"type":"link","title":null,"url":"#github","children":[{"type":"strong","children":[{"type":"text","value":"GitHub","position":{"start":{"line":4,"column":7,"offset":246},"end":{"line":4,"column":13,"offset":252},"indent":[]}}],"position":{"start":{"line":4,"column":5,"offset":244},"end":{"line":4,"column":15,"offset":254},"indent":[]}}],"position":{"start":{"line":4,"column":4,"offset":243},"end":{"line":4,"column":25,"offset":264},"indent":[]}},{"type":"text","value":" ","position":{"start":{"line":4,"column":25,"offset":264},"end":{"line":4,"column":26,"offset":265},"indent":[]}},{"type":"text","value":"—","position":{"start":{"line":4,"column":26,"offset":265},"end":{"line":4,"column":33,"offset":272},"indent":[]}},{"type":"text","value":" Ensure the safe evolution of your graph by adding schema change validation directly to your continuous integration and GitHub checks.","position":{"start":{"line":4,"column":33,"offset":272},"end":{"line":4,"column":167,"offset":406},"indent":[]}}],"position":{"start":{"line":4,"column":4,"offset":243},"end":{"line":4,"column":167,"offset":406},"indent":[]}}],"position":{"start":{"line":4,"column":1,"offset":240},"end":{"line":4,"column":167,"offset":406},"indent":[]}},{"type":"listItem","spread":false,"checked":null,"children":[{"type":"paragraph","children":[{"type":"link","title":null,"url":"#slack","children":[{"type":"strong","children":[{"type":"text","value":"Slack","position":{"start":{"line":5,"column":7,"offset":413},"end":{"line":5,"column":12,"offset":418},"indent":[]}}],"position":{"start":{"line":5,"column":5,"offset":411},"end":{"line":5,"column":14,"offset":420},"indent":[]}}],"position":{"start":{"line":5,"column":4,"offset":410},"end":{"line":5,"column":23,"offset":429},"indent":[]}},{"type":"text","value":" ","position":{"start":{"line":5,"column":23,"offset":429},"end":{"line":5,"column":24,"offset":430},"indent":[]}},{"type":"text","value":"—","position":{"start":{"line":5,"column":24,"offset":430},"end":{"line":5,"column":31,"offset":437},"indent":[]}},{"type":"text","value":" Get a daily summary of key information from your server, including the overall request rate, error rate, and performance latency. Set up notifications for noteworthy events in your service, like increases in errors or particularly slow response times for important queries.","position":{"start":{"line":5,"column":31,"offset":437},"end":{"line":5,"column":305,"offset":711},"indent":[]}}],"position":{"start":{"line":5,"column":4,"offset":410},"end":{"line":5,"column":305,"offset":711},"indent":[]}}],"position":{"start":{"line":5,"column":1,"offset":407},"end":{"line":5,"column":305,"offset":711},"indent":[]}},{"type":"listItem","spread":false,"checked":null,"children":[{"type":"paragraph","children":[{"type":"link","title":null,"url":"#datadog","children":[{"type":"strong","children":[{"type":"text","value":"Datadog","position":{"start":{"line":6,"column":7,"offset":718},"end":{"line":6,"column":14,"offset":725},"indent":[]}}],"position":{"start":{"line":6,"column":5,"offset":716},"end":{"line":6,"column":16,"offset":727},"indent":[]}}],"position":{"start":{"line":6,"column":4,"offset":715},"end":{"line":6,"column":27,"offset":738},"indent":[]}},{"type":"text","value":" ","position":{"start":{"line":6,"column":27,"offset":738},"end":{"line":6,"column":28,"offset":739},"indent":[]}},{"type":"text","value":"—","position":{"start":{"line":6,"column":28,"offset":739},"end":{"line":6,"column":35,"offset":746},"indent":[]}},{"type":"text","value":" Forward the key metrics and performance data available from Engine to Datadog as well.","position":{"start":{"line":6,"column":35,"offset":746},"end":{"line":6,"column":122,"offset":833},"indent":[]}}],"position":{"start":{"line":6,"column":4,"offset":715},"end":{"line":6,"column":122,"offset":833},"indent":[]}}],"position":{"start":{"line":6,"column":1,"offset":712},"end":{"line":6,"column":122,"offset":833},"indent":[]}}],"position":{"start":{"line":4,"column":1,"offset":240},"end":{"line":6,"column":122,"offset":833},"indent":[1,1]}},{"type":"heading","depth":2,"children":[{"type":"link","url":"#github","title":null,"data":{"hProperties":{"aria-label":"github permalink","class":"anchor"},"hChildren":[{"type":"raw","value":"<svg aria-hidden=\"true\" focusable=\"false\" height=\"16\" version=\"1.1\" viewBox=\"0 0 16 16\" width=\"16\"><path fill-rule=\"evenodd\" d=\"M4 9h1v1H4c-1.5 0-3-1.69-3-3.5S2.55 3 4 3h4c1.45 0 3 1.69 3 3.5 0 1.41-.91 2.72-2 3.25V8.59c.58-.45 1-1.27 1-2.09C10 5.22 8.98 4 8 4H4c-.98 0-2 1.22-2 2.5S3 9 4 9zm9-3h-1v1h1c1 0 2 1.22 2 2.5S13.98 12 13 12H9c-.98 0-2-1.22-2-2.5 0-.83.42-1.64 1-2.09V6.25c-1.09.53-2 1.84-2 3.25C6 11.31 7.55 13 9 13h4c1.45 0 3-1.69 3-3.5S14.5 6 13 6z\"></path></svg>"}]}},{"type":"text","value":"GitHub","position":{"start":{"line":8,"column":4,"offset":838},"end":{"line":8,"column":10,"offset":844},"indent":[]}}],"position":{"start":{"line":8,"column":1,"offset":835},"end":{"line":8,"column":10,"offset":844},"indent":[]},"data":{"id":"github","htmlAttributes":{"id":"github"},"hProperties":{"id":"github"}}},{"type":"paragraph","children":[{"type":"text","value":"Building tools to help you safely collaborate on the evolution of your graph is one of our biggest focuses at Warthog. To make ","position":{"start":{"line":10,"column":1,"offset":846},"end":{"line":10,"column":128,"offset":973},"indent":[]}},{"type":"link","title":null,"url":"/platform/schema-validation/","children":[{"type":"text","value":"schema change validation","position":{"start":{"line":10,"column":129,"offset":974},"end":{"line":10,"column":153,"offset":998},"indent":[]}}],"position":{"start":{"line":10,"column":128,"offset":973},"end":{"line":10,"column":184,"offset":1029},"indent":[]}},{"type":"text","value":" as easy to set up as possible, we've built an Warthog app for GitHub that provides status checks on pull requests when schema changes are proposed.","position":{"start":{"line":10,"column":184,"offset":1029},"end":{"line":10,"column":332,"offset":1177},"indent":[]}}],"position":{"start":{"line":10,"column":1,"offset":846},"end":{"line":10,"column":332,"offset":1177},"indent":[]}},{"type":"paragraph","children":[{"type":"image","title":null,"url":"/github-check-4a4238da8832c31605332a6a09ebd4b5.png","alt":"GitHub Status View","position":{"start":{"line":12,"column":1,"offset":1179},"end":{"line":12,"column":65,"offset":1243},"indent":[]}}],"position":{"start":{"line":12,"column":1,"offset":1179},"end":{"line":12,"column":65,"offset":1243},"indent":[]}},{"type":"heading","depth":3,"children":[{"type":"link","url":"#install-the-github-application","title":null,"data":{"hProperties":{"aria-label":"install the github application permalink","class":"anchor"},"hChildren":[{"type":"raw","value":"<svg aria-hidden=\"true\" focusable=\"false\" height=\"16\" version=\"1.1\" viewBox=\"0 0 16 16\" width=\"16\"><path fill-rule=\"evenodd\" d=\"M4 9h1v1H4c-1.5 0-3-1.69-3-3.5S2.55 3 4 3h4c1.45 0 3 1.69 3 3.5 0 1.41-.91 2.72-2 3.25V8.59c.58-.45 1-1.27 1-2.09C10 5.22 8.98 4 8 4H4c-.98 0-2 1.22-2 2.5S3 9 4 9zm9-3h-1v1h1c1 0 2 1.22 2 2.5S13.98 12 13 12H9c-.98 0-2-1.22-2-2.5 0-.83.42-1.64 1-2.09V6.25c-1.09.53-2 1.84-2 3.25C6 11.31 7.55 13 9 13h4c1.45 0 3-1.69 3-3.5S14.5 6 13 6z\"></path></svg>"}]}},{"type":"text","value":"Install the GitHub application","position":{"start":{"line":14,"column":5,"offset":1249},"end":{"line":14,"column":35,"offset":1279},"indent":[]}}],"position":{"start":{"line":14,"column":1,"offset":1245},"end":{"line":14,"column":35,"offset":1279},"indent":[]},"data":{"id":"install-the-github-application","htmlAttributes":{"id":"install-the-github-application"},"hProperties":{"id":"install-the-github-application"}}},{"type":"paragraph","children":[{"type":"text","value":"Go to ","position":{"start":{"line":16,"column":1,"offset":1281},"end":{"line":16,"column":7,"offset":1287},"indent":[]}},{"type":"link","title":null,"url":"https://github.com/apps/warthog-engine","children":[{"type":"text","value":"https://github.com/apps/warthog-engine","position":{"start":{"line":16,"column":8,"offset":1288},"end":{"line":16,"column":46,"offset":1326},"indent":[]}}],"position":{"start":{"line":16,"column":7,"offset":1287},"end":{"line":16,"column":87,"offset":1367},"indent":[]}},{"type":"text","value":" and click the ","position":{"start":{"line":16,"column":87,"offset":1367},"end":{"line":16,"column":102,"offset":1382},"indent":[]}},{"type":"html","value":"<code class=\"language-text\">Configure</code>","position":{"start":{"line":16,"column":102,"offset":1382},"end":{"line":16,"column":113,"offset":1393},"indent":[]}},{"type":"text","value":" button to install the Warthog Engine integration on the GitHub profile or organization that you want to set up checks for.","position":{"start":{"line":16,"column":113,"offset":1393},"end":{"line":16,"column":236,"offset":1516},"indent":[]}}],"position":{"start":{"line":16,"column":1,"offset":1281},"end":{"line":16,"column":236,"offset":1516},"indent":[]}},{"type":"heading","depth":3,"children":[{"type":"link","url":"#run-validation-on-each-commit","title":null,"data":{"hProperties":{"aria-label":"run validation on each commit permalink","class":"anchor"},"hChildren":[{"type":"raw","value":"<svg aria-hidden=\"true\" focusable=\"false\" height=\"16\" version=\"1.1\" viewBox=\"0 0 16 16\" width=\"16\"><path fill-rule=\"evenodd\" d=\"M4 9h1v1H4c-1.5 0-3-1.69-3-3.5S2.55 3 4 3h4c1.45 0 3 1.69 3 3.5 0 1.41-.91 2.72-2 3.25V8.59c.58-.45 1-1.27 1-2.09C10 5.22 8.98 4 8 4H4c-.98 0-2 1.22-2 2.5S3 9 4 9zm9-3h-1v1h1c1 0 2 1.22 2 2.5S13.98 12 13 12H9c-.98 0-2-1.22-2-2.5 0-.83.42-1.64 1-2.09V6.25c-1.09.53-2 1.84-2 3.25C6 11.31 7.55 13 9 13h4c1.45 0 3-1.69 3-3.5S14.5 6 13 6z\"></path></svg>"}]}},{"type":"text","value":"Run validation on each commit","position":{"start":{"line":18,"column":5,"offset":1522},"end":{"line":18,"column":34,"offset":1551},"indent":[]}}],"position":{"start":{"line":18,"column":1,"offset":1518},"end":{"line":18,"column":34,"offset":1551},"indent":[]},"data":{"id":"run-validation-on-each-commit","htmlAttributes":{"id":"run-validation-on-each-commit"},"hProperties":{"id":"run-validation-on-each-commit"}}},{"type":"paragraph","children":[{"type":"text","value":"Next, make sure your CI has a step to run the schema validation command. This is accomplished by adding the ","position":{"start":{"line":20,"column":1,"offset":1553},"end":{"line":20,"column":109,"offset":1661},"indent":[]}},{"type":"html","value":"<code class=\"language-text\">warthog schema:check</code>","position":{"start":{"line":20,"column":109,"offset":1661},"end":{"line":20,"column":131,"offset":1683},"indent":[]}},{"type":"text","value":" command directly as a step in your CI. For CircleCI it could look something like this:","position":{"start":{"line":20,"column":131,"offset":1683},"end":{"line":20,"column":218,"offset":1770},"indent":[]}}],"position":{"start":{"line":20,"column":1,"offset":1553},"end":{"line":20,"column":218,"offset":1770},"indent":[]}},{"type":"html","lang":"yaml{13,29,33-36}","meta":null,"value":"<div class=\"gatsby-highlight has-highlighted-lines\" data-language=\"yaml\"><pre style=\"counter-reset: linenumber NaN\" class=\"language-yaml line-numbers\"><code class=\"language-yaml\"><span class=\"token key atrule\">version</span><span class=\"token punctuation\">:</span> <span class=\"token number\">2</span>\n\n<span class=\"token key atrule\">jobs</span><span class=\"token punctuation\">:</span>\n  <span class=\"token key atrule\">build</span><span class=\"token punctuation\">:</span>\n    <span class=\"token key atrule\">docker</span><span class=\"token punctuation\">:</span>\n      <span class=\"token punctuation\">-</span> <span class=\"token key atrule\">image</span><span class=\"token punctuation\">:</span> circleci/node<span class=\"token punctuation\">:</span><span class=\"token number\">8</span>\n\n    <span class=\"token key atrule\">steps</span><span class=\"token punctuation\">:</span>\n      <span class=\"token punctuation\">-</span> checkout\n\n      <span class=\"token punctuation\">-</span> <span class=\"token key atrule\">run</span><span class=\"token punctuation\">:</span> npm install\n      <span class=\"token comment\"># CircleCI needs global installs to be sudo</span>\n<span class=\"gatsby-highlight-code-line\">      <span class=\"token punctuation\">-</span> <span class=\"token key atrule\">run</span><span class=\"token punctuation\">:</span> sudo npm install <span class=\"token punctuation\">-</span><span class=\"token punctuation\">-</span>global warthog</span>\n      <span class=\"token comment\"># Start the GraphQL server.  If a different command is used to</span>\n      <span class=\"token comment\"># start the server, use it in place of `npm start` here.</span>\n      <span class=\"token punctuation\">-</span> <span class=\"token key atrule\">run</span><span class=\"token punctuation\">:</span>\n          <span class=\"token key atrule\">name</span><span class=\"token punctuation\">:</span> Starting server\n          <span class=\"token key atrule\">command</span><span class=\"token punctuation\">:</span> npm start\n          <span class=\"token key atrule\">background</span><span class=\"token punctuation\">:</span> <span class=\"token boolean important\">true</span>\n\n      <span class=\"token comment\"># make sure the server has enough time to start up before running</span>\n      <span class=\"token comment\"># commands against it</span>\n      <span class=\"token punctuation\">-</span> <span class=\"token key atrule\">run</span><span class=\"token punctuation\">:</span> sleep 5\n\n      <span class=\"token comment\"># This will authenticate using the `ENGINE_API_KEY` environment</span>\n      <span class=\"token comment\"># variable. If the GraphQL server is available elsewhere than</span>\n      <span class=\"token comment\"># http://localhost:4000/graphql, set it with `--endpoint=&lt;URL>`.</span>\n<span class=\"gatsby-highlight-code-line\">      <span class=\"token punctuation\">-</span> <span class=\"token key atrule\">run</span><span class=\"token punctuation\">:</span> warthog service<span class=\"token punctuation\">:</span>check</span>\n      <span class=\"token comment\"># When running on the 'master' branch, publish the latest version</span>\n      <span class=\"token comment\"># of the schema to Warthog Engine.</span>\n<span class=\"gatsby-highlight-code-line\">      <span class=\"token punctuation\">-</span> <span class=\"token key atrule\">run</span><span class=\"token punctuation\">:</span> <span class=\"token punctuation\">|</span><span class=\"token scalar string\"></span><span class=\"gatsby-highlight-code-line\">          if [ \"${CIRCLE_BRANCH}\" == \"master\" ]; then</span><span class=\"gatsby-highlight-code-line\">            warthog service:push</span><span class=\"gatsby-highlight-code-line\">          fi</span></span></code><span aria-hidden=\"true\" class=\"line-numbers-rows\" style=\"white-space: normal; width: auto; left: 0;\"><span></span><span></span><span></span><span></span><span></span><span></span><span></span><span></span><span></span><span></span><span></span><span></span><span></span><span></span><span></span><span></span><span></span><span></span><span></span><span></span><span></span><span></span><span></span><span></span><span></span><span></span><span></span><span></span><span></span><span></span><span></span><span></span><span></span><span></span><span></span><span></span></span></pre></div>","position":{"start":{"line":22,"column":1,"offset":1772},"end":{"line":59,"column":4,"offset":2848},"indent":[1,1,1,1,1,1,1,1,1,1,1,1,1,1,1,1,1,1,1,1,1,1,1,1,1,1,1,1,1,1,1,1,1,1,1,1,1]}},{"type":"blockquote","children":[{"type":"paragraph","children":[{"type":"strong","children":[{"type":"text","value":"Note:","position":{"start":{"line":61,"column":5,"offset":2854},"end":{"line":61,"column":10,"offset":2859},"indent":[]}}],"position":{"start":{"line":61,"column":3,"offset":2852},"end":{"line":61,"column":12,"offset":2861},"indent":[]}},{"type":"text","value":" Your ","position":{"start":{"line":61,"column":12,"offset":2861},"end":{"line":61,"column":18,"offset":2867},"indent":[]}},{"type":"html","value":"<code class=\"language-text\">warthog service:check</code>","position":{"start":{"line":61,"column":18,"offset":2867},"end":{"line":61,"column":41,"offset":2890},"indent":[]}},{"type":"text","value":" command needs a source to from which to fetch your schema. This is most commonly provided as a URL to a running server (with introspection enabled), but can also be provided as a path to a file with your schema in it. See ","position":{"start":{"line":61,"column":41,"offset":2890},"end":{"line":61,"column":264,"offset":3113},"indent":[]}},{"type":"link","title":null,"url":"/platform/schema-registry/#using-the-schema-registry","children":[{"type":"text","value":"Using the Schema Registry","position":{"start":{"line":61,"column":265,"offset":3114},"end":{"line":61,"column":290,"offset":3139},"indent":[]}}],"position":{"start":{"line":61,"column":264,"offset":3113},"end":{"line":61,"column":345,"offset":3194},"indent":[]}},{"type":"text","value":" setup for other options.","position":{"start":{"line":61,"column":345,"offset":3194},"end":{"line":61,"column":370,"offset":3219},"indent":[]}}],"position":{"start":{"line":61,"column":3,"offset":2852},"end":{"line":61,"column":370,"offset":3219},"indent":[]}}],"position":{"start":{"line":61,"column":1,"offset":2850},"end":{"line":61,"column":370,"offset":3219},"indent":[]}},{"type":"paragraph","children":[{"type":"text","value":"The ","position":{"start":{"line":63,"column":1,"offset":3221},"end":{"line":63,"column":5,"offset":3225},"indent":[]}},{"type":"html","value":"<code class=\"language-text\">warthog schema:check</code>","position":{"start":{"line":63,"column":5,"offset":3225},"end":{"line":63,"column":27,"offset":3247},"indent":[]}},{"type":"text","value":" command checks for differences in your schema between what's on your current branch and the last version you uploaded to Engine. If you've removed or changed any types or fields, it will validate that those changes won't break any of the queries that your clients have made recently. If your changes do break any queries, the check will fail.","position":{"start":{"line":63,"column":27,"offset":3247},"end":{"line":63,"column":370,"offset":3590},"indent":[]}}],"position":{"start":{"line":63,"column":1,"offset":3221},"end":{"line":63,"column":370,"offset":3590},"indent":[]}},{"type":"paragraph","children":[{"type":"text","value":"Because you installed the Engine app on GitHub, the check you've added will show up as a line in your GitHub checks list. If there are changes in your schema you'll be able to review them by clicking the \"Details\" link. By enabling schema validation in your continuous integration workflow (eg. CircleCI, etc.), you're alerting developers of any potential problems directly in their pull requests, thereby giving them critical feedback where it's most useful.","position":{"start":{"line":65,"column":1,"offset":3592},"end":{"line":65,"column":460,"offset":4051},"indent":[]}}],"position":{"start":{"line":65,"column":1,"offset":3592},"end":{"line":65,"column":460,"offset":4051},"indent":[]}},{"type":"heading","depth":2,"children":[{"type":"link","url":"#slack","title":null,"data":{"hProperties":{"aria-label":"slack permalink","class":"anchor"},"hChildren":[{"type":"raw","value":"<svg aria-hidden=\"true\" focusable=\"false\" height=\"16\" version=\"1.1\" viewBox=\"0 0 16 16\" width=\"16\"><path fill-rule=\"evenodd\" d=\"M4 9h1v1H4c-1.5 0-3-1.69-3-3.5S2.55 3 4 3h4c1.45 0 3 1.69 3 3.5 0 1.41-.91 2.72-2 3.25V8.59c.58-.45 1-1.27 1-2.09C10 5.22 8.98 4 8 4H4c-.98 0-2 1.22-2 2.5S3 9 4 9zm9-3h-1v1h1c1 0 2 1.22 2 2.5S13.98 12 13 12H9c-.98 0-2-1.22-2-2.5 0-.83.42-1.64 1-2.09V6.25c-1.09.53-2 1.84-2 3.25C6 11.31 7.55 13 9 13h4c1.45 0 3-1.69 3-3.5S14.5 6 13 6z\"></path></svg>"}]}},{"type":"text","value":"Slack","position":{"start":{"line":67,"column":4,"offset":4056},"end":{"line":67,"column":9,"offset":4061},"indent":[]}}],"position":{"start":{"line":67,"column":1,"offset":4053},"end":{"line":67,"column":9,"offset":4061},"indent":[]},"data":{"id":"slack","htmlAttributes":{"id":"slack"},"hProperties":{"id":"slack"}}},{"type":"paragraph","children":[{"type":"text","value":"Our Warthog Slack integration brings your server's performance metrics and analytics data from Warthog Engine directly to your team's Slack workspace so you can be notified of potential issues proactively. The integration does two main things:","position":{"start":{"line":69,"column":1,"offset":4063},"end":{"line":69,"column":244,"offset":4306},"indent":[]}}],"position":{"start":{"line":69,"column":1,"offset":4063},"end":{"line":69,"column":244,"offset":4306},"indent":[]}},{"type":"list","ordered":true,"start":1,"spread":false,"children":[{"type":"listItem","spread":false,"checked":null,"children":[{"type":"paragraph","children":[{"type":"text","value":"Send a ","position":{"start":{"line":71,"column":4,"offset":4311},"end":{"line":71,"column":11,"offset":4318},"indent":[]}},{"type":"link","title":null,"url":"#daily-reports","children":[{"type":"strong","children":[{"type":"text","value":"daily snapshot","position":{"start":{"line":71,"column":14,"offset":4321},"end":{"line":71,"column":28,"offset":4335},"indent":[]}}],"position":{"start":{"line":71,"column":12,"offset":4319},"end":{"line":71,"column":30,"offset":4337},"indent":[]}}],"position":{"start":{"line":71,"column":11,"offset":4318},"end":{"line":71,"column":47,"offset":4354},"indent":[]}},{"type":"text","value":" of the request rate, error rate, and performance latency of your graph.","position":{"start":{"line":71,"column":47,"offset":4354},"end":{"line":71,"column":119,"offset":4426},"indent":[]}}],"position":{"start":{"line":71,"column":4,"offset":4311},"end":{"line":71,"column":119,"offset":4426},"indent":[]}}],"position":{"start":{"line":71,"column":1,"offset":4308},"end":{"line":71,"column":119,"offset":4426},"indent":[]}},{"type":"listItem","spread":false,"checked":null,"children":[{"type":"paragraph","children":[{"type":"text","value":"Send ","position":{"start":{"line":72,"column":4,"offset":4430},"end":{"line":72,"column":9,"offset":4435},"indent":[]}},{"type":"link","title":null,"url":"#notifications","children":[{"type":"strong","children":[{"type":"text","value":"notifications","position":{"start":{"line":72,"column":12,"offset":4438},"end":{"line":72,"column":25,"offset":4451},"indent":[]}}],"position":{"start":{"line":72,"column":10,"offset":4436},"end":{"line":72,"column":27,"offset":4453},"indent":[]}}],"position":{"start":{"line":72,"column":9,"offset":4435},"end":{"line":72,"column":44,"offset":4470},"indent":[]}},{"type":"text","value":" that are triggered on thresholds like error percentage and performance latency.","position":{"start":{"line":72,"column":44,"offset":4470},"end":{"line":72,"column":124,"offset":4550},"indent":[]}}],"position":{"start":{"line":72,"column":4,"offset":4430},"end":{"line":72,"column":124,"offset":4550},"indent":[]}}],"position":{"start":{"line":72,"column":1,"offset":4427},"end":{"line":72,"column":124,"offset":4550},"indent":[]}}],"position":{"start":{"line":71,"column":1,"offset":4308},"end":{"line":72,"column":124,"offset":4550},"indent":[1]}},{"type":"heading","depth":3,"children":[{"type":"link","url":"#configure-the-integration","title":null,"data":{"hProperties":{"aria-label":"configure the integration permalink","class":"anchor"},"hChildren":[{"type":"raw","value":"<svg aria-hidden=\"true\" focusable=\"false\" height=\"16\" version=\"1.1\" viewBox=\"0 0 16 16\" width=\"16\"><path fill-rule=\"evenodd\" d=\"M4 9h1v1H4c-1.5 0-3-1.69-3-3.5S2.55 3 4 3h4c1.45 0 3 1.69 3 3.5 0 1.41-.91 2.72-2 3.25V8.59c.58-.45 1-1.27 1-2.09C10 5.22 8.98 4 8 4H4c-.98 0-2 1.22-2 2.5S3 9 4 9zm9-3h-1v1h1c1 0 2 1.22 2 2.5S13.98 12 13 12H9c-.98 0-2-1.22-2-2.5 0-.83.42-1.64 1-2.09V6.25c-1.09.53-2 1.84-2 3.25C6 11.31 7.55 13 9 13h4c1.45 0 3-1.69 3-3.5S14.5 6 13 6z\"></path></svg>"}]}},{"type":"text","value":"Configure the integration","position":{"start":{"line":74,"column":5,"offset":4556},"end":{"line":74,"column":30,"offset":4581},"indent":[]}}],"position":{"start":{"line":74,"column":1,"offset":4552},"end":{"line":74,"column":30,"offset":4581},"indent":[]},"data":{"id":"configure-the-integration","htmlAttributes":{"id":"configure-the-integration"},"hProperties":{"id":"configure-the-integration"}}},{"type":"paragraph","children":[{"type":"text","value":"The Warthog Slack integration is set up and configured through the Engine UI. If you do not yet have account, ","position":{"start":{"line":76,"column":1,"offset":4583},"end":{"line":76,"column":111,"offset":4693},"indent":[]}},{"type":"link","title":null,"url":"https://www.warthog.dev/docs/warthog-server/features/metrics/#Warthog-Engine","children":[{"type":"strong","children":[{"type":"text","value":"follow this guide","position":{"start":{"line":76,"column":114,"offset":4696},"end":{"line":76,"column":131,"offset":4713},"indent":[]}}],"position":{"start":{"line":76,"column":112,"offset":4694},"end":{"line":76,"column":133,"offset":4715},"indent":[]}}],"position":{"start":{"line":76,"column":111,"offset":4693},"end":{"line":76,"column":212,"offset":4794},"indent":[]}},{"type":"text","value":" to get started connecting your server to Engine.","position":{"start":{"line":76,"column":212,"offset":4794},"end":{"line":76,"column":261,"offset":4843},"indent":[]}}],"position":{"start":{"line":76,"column":1,"offset":4583},"end":{"line":76,"column":261,"offset":4843},"indent":[]}},{"type":"paragraph","children":[{"type":"text","value":"If you already have an Engine account, ","position":{"start":{"line":78,"column":1,"offset":4845},"end":{"line":78,"column":40,"offset":4884},"indent":[]}},{"type":"link","title":null,"url":"https://engine.warthog.dev","children":[{"type":"strong","children":[{"type":"text","value":"log in","position":{"start":{"line":78,"column":43,"offset":4887},"end":{"line":78,"column":49,"offset":4893},"indent":[]}}],"position":{"start":{"line":78,"column":41,"offset":4885},"end":{"line":78,"column":51,"offset":4895},"indent":[]}}],"position":{"start":{"line":78,"column":40,"offset":4884},"end":{"line":78,"column":80,"offset":4924},"indent":[]}},{"type":"text","value":" and ––","position":{"start":{"line":78,"column":80,"offset":4924},"end":{"line":78,"column":87,"offset":4931},"indent":[]}}],"position":{"start":{"line":78,"column":1,"offset":4845},"end":{"line":78,"column":87,"offset":4931},"indent":[]}},{"type":"list","ordered":true,"start":1,"spread":false,"children":[{"type":"listItem","spread":false,"checked":null,"children":[{"type":"paragraph","children":[{"type":"text","value":"Select the service you want to turn on Slack notifications for.","position":{"start":{"line":80,"column":4,"offset":4936},"end":{"line":80,"column":67,"offset":4999},"indent":[]}}],"position":{"start":{"line":80,"column":4,"offset":4936},"end":{"line":80,"column":67,"offset":4999},"indent":[]}}],"position":{"start":{"line":80,"column":1,"offset":4933},"end":{"line":80,"column":67,"offset":4999},"indent":[]}},{"type":"listItem","spread":false,"checked":null,"children":[{"type":"paragraph","children":[{"type":"text","value":"Visit the \"Integrations\" tab in the left nav.","position":{"start":{"line":81,"column":4,"offset":5003},"end":{"line":81,"column":49,"offset":5048},"indent":[]}}],"position":{"start":{"line":81,"column":4,"offset":5003},"end":{"line":81,"column":49,"offset":5048},"indent":[]}}],"position":{"start":{"line":81,"column":1,"offset":5000},"end":{"line":81,"column":49,"offset":5048},"indent":[]}},{"type":"listItem","spread":false,"checked":null,"children":[{"type":"paragraph","children":[{"type":"text","value":"You'll notice a \"Reporting Channels\" section at the bottom of this page. Click the \"Add channel\" button and follow the steps in the Engine UI to get a webhook from Slack.","position":{"start":{"line":82,"column":4,"offset":5052},"end":{"line":82,"column":174,"offset":5222},"indent":[]}}],"position":{"start":{"line":82,"column":4,"offset":5052},"end":{"line":82,"column":174,"offset":5222},"indent":[]}}],"position":{"start":{"line":82,"column":1,"offset":5049},"end":{"line":82,"column":174,"offset":5222},"indent":[]}}],"position":{"start":{"line":80,"column":1,"offset":4933},"end":{"line":82,"column":174,"offset":5222},"indent":[1,1]}},{"type":"paragraph","children":[{"type":"text","value":"Once you've configured your Slack channel you'll be able to turn on daily reports snapshotting and configure notifications in the \"General\" and \"Performance Alerts\" sections.","position":{"start":{"line":84,"column":1,"offset":5224},"end":{"line":84,"column":175,"offset":5398},"indent":[]}}],"position":{"start":{"line":84,"column":1,"offset":5224},"end":{"line":84,"column":175,"offset":5398},"indent":[]}},{"type":"paragraph","children":[{"type":"image","title":null,"url":"/integrations-tab-a8d1a952049cc8969b71d90c46694442.png","alt":"The Integrations tab in Engine","position":{"start":{"line":86,"column":1,"offset":5400},"end":{"line":86,"column":76,"offset":5475},"indent":[]}}],"position":{"start":{"line":86,"column":1,"offset":5400},"end":{"line":86,"column":76,"offset":5475},"indent":[]}},{"type":"heading","depth":3,"children":[{"type":"link","url":"#daily-reports","title":null,"data":{"hProperties":{"aria-label":"daily reports permalink","class":"anchor"},"hChildren":[{"type":"raw","value":"<svg aria-hidden=\"true\" focusable=\"false\" height=\"16\" version=\"1.1\" viewBox=\"0 0 16 16\" width=\"16\"><path fill-rule=\"evenodd\" d=\"M4 9h1v1H4c-1.5 0-3-1.69-3-3.5S2.55 3 4 3h4c1.45 0 3 1.69 3 3.5 0 1.41-.91 2.72-2 3.25V8.59c.58-.45 1-1.27 1-2.09C10 5.22 8.98 4 8 4H4c-.98 0-2 1.22-2 2.5S3 9 4 9zm9-3h-1v1h1c1 0 2 1.22 2 2.5S13.98 12 13 12H9c-.98 0-2-1.22-2-2.5 0-.83.42-1.64 1-2.09V6.25c-1.09.53-2 1.84-2 3.25C6 11.31 7.55 13 9 13h4c1.45 0 3-1.69 3-3.5S14.5 6 13 6z\"></path></svg>"}]}},{"type":"text","value":"Daily reports","position":{"start":{"line":88,"column":5,"offset":5481},"end":{"line":88,"column":18,"offset":5494},"indent":[]}}],"position":{"start":{"line":88,"column":1,"offset":5477},"end":{"line":88,"column":18,"offset":5494},"indent":[]},"data":{"id":"daily-reports","htmlAttributes":{"id":"daily-reports"},"hProperties":{"id":"daily-reports"}}},{"type":"paragraph","children":[{"type":"text","value":"Daily reports from Engine are sent out around 9am in whichever timezone you configure them to be in. You turn them on in the \"Integrations\" tab as shown above. The reports have a set format that gives a birds-eye view of what your GraphQL API delivered in the previous day:","position":{"start":{"line":90,"column":1,"offset":5496},"end":{"line":90,"column":274,"offset":5769},"indent":[]}}],"position":{"start":{"line":90,"column":1,"offset":5496},"end":{"line":90,"column":274,"offset":5769},"indent":[]}},{"type":"paragraph","children":[{"type":"image","title":null,"url":"/slack-report-654aa614b7e554f9260679b149d5a261.png","alt":"Engine slack report","position":{"start":{"line":92,"column":1,"offset":5771},"end":{"line":92,"column":61,"offset":5831},"indent":[]}}],"position":{"start":{"line":92,"column":1,"offset":5771},"end":{"line":92,"column":61,"offset":5831},"indent":[]}},{"type":"heading","depth":4,"children":[{"type":"link","url":"#using-the-report","title":null,"data":{"hProperties":{"aria-label":"using the report permalink","class":"anchor"},"hChildren":[{"type":"raw","value":"<svg aria-hidden=\"true\" focusable=\"false\" height=\"16\" version=\"1.1\" viewBox=\"0 0 16 16\" width=\"16\"><path fill-rule=\"evenodd\" d=\"M4 9h1v1H4c-1.5 0-3-1.69-3-3.5S2.55 3 4 3h4c1.45 0 3 1.69 3 3.5 0 1.41-.91 2.72-2 3.25V8.59c.58-.45 1-1.27 1-2.09C10 5.22 8.98 4 8 4H4c-.98 0-2 1.22-2 2.5S3 9 4 9zm9-3h-1v1h1c1 0 2 1.22 2 2.5S13.98 12 13 12H9c-.98 0-2-1.22-2-2.5 0-.83.42-1.64 1-2.09V6.25c-1.09.53-2 1.84-2 3.25C6 11.31 7.55 13 9 13h4c1.45 0 3-1.69 3-3.5S14.5 6 13 6z\"></path></svg>"}]}},{"type":"text","value":"Using the report","position":{"start":{"line":94,"column":6,"offset":5838},"end":{"line":94,"column":22,"offset":5854},"indent":[]}}],"position":{"start":{"line":94,"column":1,"offset":5833},"end":{"line":94,"column":22,"offset":5854},"indent":[]},"data":{"id":"using-the-report","htmlAttributes":{"id":"using-the-report"},"hProperties":{"id":"using-the-report"}}},{"type":"paragraph","children":[{"type":"text","value":"We've constructed the report provided to give you an actionable summary of what's happened in your API in the last 24 hours. Here’s how you can use it to identify issues:","position":{"start":{"line":96,"column":1,"offset":5856},"end":{"line":96,"column":171,"offset":6026},"indent":[]}}],"position":{"start":{"line":96,"column":1,"offset":5856},"end":{"line":96,"column":171,"offset":6026},"indent":[]}},{"type":"list","ordered":true,"start":1,"spread":false,"children":[{"type":"listItem","spread":false,"checked":null,"children":[{"type":"paragraph","children":[{"type":"strong","children":[{"type":"text","value":"Request rate:","position":{"start":{"line":98,"column":7,"offset":6034},"end":{"line":98,"column":20,"offset":6047},"indent":[]}}],"position":{"start":{"line":98,"column":5,"offset":6032},"end":{"line":98,"column":22,"offset":6049},"indent":[]}},{"type":"text","value":" This shows you how many queries are hitting your server every minute, along with a list of the most popular operations. If you see a huge dip in this and it's usually a busy time for your app, it might mean that queries aren’t able to reach your server, or some client is down.","position":{"start":{"line":98,"column":22,"offset":6049},"end":{"line":98,"column":300,"offset":6327},"indent":[]}}],"position":{"start":{"line":98,"column":5,"offset":6032},"end":{"line":98,"column":300,"offset":6327},"indent":[]}}],"position":{"start":{"line":98,"column":1,"offset":6028},"end":{"line":98,"column":300,"offset":6327},"indent":[]}},{"type":"listItem","spread":false,"checked":null,"children":[{"type":"paragraph","children":[{"type":"strong","children":[{"type":"text","value":"p95 service time:","position":{"start":{"line":99,"column":7,"offset":6334},"end":{"line":99,"column":24,"offset":6351},"indent":[]}}],"position":{"start":{"line":99,"column":5,"offset":6332},"end":{"line":99,"column":26,"offset":6353},"indent":[]}},{"type":"text","value":" This shows you how long queries are taking to execute. We selected p95 since it’s the best overall representation of how your users are experiencing your app. You can use this to identify that your API is overloaded and users are seeing long loading delays, or to find out which queries are taking the longest to run. This is usually directly connected to UI performance, so a 500ms query probably means some part of your UI is taking that long to display.","position":{"start":{"line":99,"column":26,"offset":6353},"end":{"line":99,"column":483,"offset":6810},"indent":[]}}],"position":{"start":{"line":99,"column":5,"offset":6332},"end":{"line":99,"column":483,"offset":6810},"indent":[]}}],"position":{"start":{"line":99,"column":1,"offset":6328},"end":{"line":99,"column":483,"offset":6810},"indent":[]}},{"type":"listItem","spread":false,"checked":null,"children":[{"type":"paragraph","children":[{"type":"strong","children":[{"type":"text","value":"Error percentage:","position":{"start":{"line":100,"column":7,"offset":6817},"end":{"line":100,"column":24,"offset":6834},"indent":[]}}],"position":{"start":{"line":100,"column":5,"offset":6815},"end":{"line":100,"column":26,"offset":6836},"indent":[]}},{"type":"text","value":" This will show you how many of your GraphQL requests end up with an error result. Spikes in errors might be the result of some underlying backend malfunctioning. You can also see which of your operations are most error-prone.","position":{"start":{"line":100,"column":26,"offset":6836},"end":{"line":100,"column":252,"offset":7062},"indent":[]}}],"position":{"start":{"line":100,"column":5,"offset":6815},"end":{"line":100,"column":252,"offset":7062},"indent":[]}}],"position":{"start":{"line":100,"column":1,"offset":6811},"end":{"line":100,"column":252,"offset":7062},"indent":[]}}],"position":{"start":{"line":98,"column":1,"offset":6028},"end":{"line":100,"column":252,"offset":7062},"indent":[1,1]}},{"type":"heading","depth":3,"children":[{"type":"link","url":"#notifications","title":null,"data":{"hProperties":{"aria-label":"notifications permalink","class":"anchor"},"hChildren":[{"type":"raw","value":"<svg aria-hidden=\"true\" focusable=\"false\" height=\"16\" version=\"1.1\" viewBox=\"0 0 16 16\" width=\"16\"><path fill-rule=\"evenodd\" d=\"M4 9h1v1H4c-1.5 0-3-1.69-3-3.5S2.55 3 4 3h4c1.45 0 3 1.69 3 3.5 0 1.41-.91 2.72-2 3.25V8.59c.58-.45 1-1.27 1-2.09C10 5.22 8.98 4 8 4H4c-.98 0-2 1.22-2 2.5S3 9 4 9zm9-3h-1v1h1c1 0 2 1.22 2 2.5S13.98 12 13 12H9c-.98 0-2-1.22-2-2.5 0-.83.42-1.64 1-2.09V6.25c-1.09.53-2 1.84-2 3.25C6 11.31 7.55 13 9 13h4c1.45 0 3-1.69 3-3.5S14.5 6 13 6z\"></path></svg>"}]}},{"type":"text","value":"Notifications","position":{"start":{"line":102,"column":5,"offset":7068},"end":{"line":102,"column":18,"offset":7081},"indent":[]}}],"position":{"start":{"line":102,"column":1,"offset":7064},"end":{"line":102,"column":18,"offset":7081},"indent":[]},"data":{"id":"notifications","htmlAttributes":{"id":"notifications"},"hProperties":{"id":"notifications"}}},{"type":"paragraph","children":[{"type":"text","value":"In Engine you can configure notifications that are triggered on the performance data of your graph, like error percentages and request latencies. This is particularly useful for detecting anomalies, especially around releases. Notifications can be configured to monitor the following metrics for either your entire GraphQL service or individual operations:","position":{"start":{"line":104,"column":1,"offset":7083},"end":{"line":104,"column":357,"offset":7439},"indent":[]}}],"position":{"start":{"line":104,"column":1,"offset":7083},"end":{"line":104,"column":357,"offset":7439},"indent":[]}},{"type":"list","ordered":false,"start":null,"spread":false,"children":[{"type":"listItem","spread":false,"checked":null,"children":[{"type":"paragraph","children":[{"type":"strong","children":[{"type":"text","value":"Request rate:","position":{"start":{"line":106,"column":5,"offset":7445},"end":{"line":106,"column":18,"offset":7458},"indent":[]}}],"position":{"start":{"line":106,"column":3,"offset":7443},"end":{"line":106,"column":20,"offset":7460},"indent":[]}},{"type":"text","value":"  requests per minute","position":{"start":{"line":106,"column":20,"offset":7460},"end":{"line":106,"column":41,"offset":7481},"indent":[]}}],"position":{"start":{"line":106,"column":3,"offset":7443},"end":{"line":106,"column":41,"offset":7481},"indent":[]}}],"position":{"start":{"line":106,"column":1,"offset":7441},"end":{"line":106,"column":41,"offset":7481},"indent":[]}},{"type":"listItem","spread":false,"checked":null,"children":[{"type":"paragraph","children":[{"type":"strong","children":[{"type":"text","value":"Request duration:","position":{"start":{"line":107,"column":5,"offset":7486},"end":{"line":107,"column":22,"offset":7503},"indent":[]}}],"position":{"start":{"line":107,"column":3,"offset":7484},"end":{"line":107,"column":24,"offset":7505},"indent":[]}},{"type":"text","value":" p50/p95/p99 service time","position":{"start":{"line":107,"column":24,"offset":7505},"end":{"line":107,"column":49,"offset":7530},"indent":[]}}],"position":{"start":{"line":107,"column":3,"offset":7484},"end":{"line":107,"column":49,"offset":7530},"indent":[]}}],"position":{"start":{"line":107,"column":1,"offset":7482},"end":{"line":107,"column":49,"offset":7530},"indent":[]}},{"type":"listItem","spread":false,"checked":null,"children":[{"type":"paragraph","children":[{"type":"strong","children":[{"type":"text","value":"Error rate:","position":{"start":{"line":108,"column":5,"offset":7535},"end":{"line":108,"column":16,"offset":7546},"indent":[]}}],"position":{"start":{"line":108,"column":3,"offset":7533},"end":{"line":108,"column":18,"offset":7548},"indent":[]}},{"type":"text","value":" errors per minute","position":{"start":{"line":108,"column":18,"offset":7548},"end":{"line":108,"column":36,"offset":7566},"indent":[]}}],"position":{"start":{"line":108,"column":3,"offset":7533},"end":{"line":108,"column":36,"offset":7566},"indent":[]}}],"position":{"start":{"line":108,"column":1,"offset":7531},"end":{"line":108,"column":36,"offset":7566},"indent":[]}},{"type":"listItem","spread":false,"checked":null,"children":[{"type":"paragraph","children":[{"type":"strong","children":[{"type":"text","value":"Error percentage:","position":{"start":{"line":109,"column":5,"offset":7571},"end":{"line":109,"column":22,"offset":7588},"indent":[]}}],"position":{"start":{"line":109,"column":3,"offset":7569},"end":{"line":109,"column":24,"offset":7590},"indent":[]}},{"type":"text","value":" the number of requests with errors, divided by total\nrequests","position":{"start":{"line":109,"column":24,"offset":7590},"end":{"line":110,"column":11,"offset":7654},"indent":[3]}}],"position":{"start":{"line":109,"column":3,"offset":7569},"end":{"line":110,"column":11,"offset":7654},"indent":[3]}}],"position":{"start":{"line":109,"column":1,"offset":7567},"end":{"line":110,"column":11,"offset":7654},"indent":[1]}}],"position":{"start":{"line":106,"column":1,"offset":7441},"end":{"line":110,"column":11,"offset":7654},"indent":[1,1,1,1]}},{"type":"paragraph","children":[{"type":"text","value":"The triggers you set up are evaluated on a rolling five minute window. For example, you can configure a notification to trigger when an operation's error rate exceeds 5%. In production, if 6 out of 100 requests result in an error during the last five minutes, the alert will trigger with an error rate of 6%. Once the error rate falls back below 5% your notification will resolve. Here's an example of what the notification looks like:","position":{"start":{"line":112,"column":1,"offset":7656},"end":{"line":112,"column":436,"offset":8091},"indent":[]}}],"position":{"start":{"line":112,"column":1,"offset":7656},"end":{"line":112,"column":436,"offset":8091},"indent":[]}},{"type":"paragraph","children":[{"type":"image","title":null,"url":"/slack-notification-4da2300985e218ab800eff749821c818.png","alt":"Slack Alert","position":{"start":{"line":114,"column":1,"offset":8093},"end":{"line":114,"column":59,"offset":8151},"indent":[]}}],"position":{"start":{"line":114,"column":1,"offset":8093},"end":{"line":114,"column":59,"offset":8151},"indent":[]}},{"type":"heading","depth":2,"children":[{"type":"link","url":"#datadog","title":null,"data":{"hProperties":{"aria-label":"datadog permalink","class":"anchor"},"hChildren":[{"type":"raw","value":"<svg aria-hidden=\"true\" focusable=\"false\" height=\"16\" version=\"1.1\" viewBox=\"0 0 16 16\" width=\"16\"><path fill-rule=\"evenodd\" d=\"M4 9h1v1H4c-1.5 0-3-1.69-3-3.5S2.55 3 4 3h4c1.45 0 3 1.69 3 3.5 0 1.41-.91 2.72-2 3.25V8.59c.58-.45 1-1.27 1-2.09C10 5.22 8.98 4 8 4H4c-.98 0-2 1.22-2 2.5S3 9 4 9zm9-3h-1v1h1c1 0 2 1.22 2 2.5S13.98 12 13 12H9c-.98 0-2-1.22-2-2.5 0-.83.42-1.64 1-2.09V6.25c-1.09.53-2 1.84-2 3.25C6 11.31 7.55 13 9 13h4c1.45 0 3-1.69 3-3.5S14.5 6 13 6z\"></path></svg>"}]}},{"type":"text","value":"Datadog","position":{"start":{"line":116,"column":4,"offset":8156},"end":{"line":116,"column":11,"offset":8163},"indent":[]}}],"position":{"start":{"line":116,"column":1,"offset":8153},"end":{"line":116,"column":11,"offset":8163},"indent":[]},"data":{"id":"datadog","htmlAttributes":{"id":"datadog"},"hProperties":{"id":"datadog"}}},{"type":"paragraph","children":[{"type":"text","value":"The Warthog Datadog integration allows you to forward all the performance metrics and analytics data that's available to you in Engine to Datadog as well. This is particularly convenient for teams already relying on Datadog for their monitoring, and of the best perks is that Datadog has advanced filtering features that alerts can be set on, and teams can set those alerts based on their GraphQL metrics data from Engine through Datadog.","position":{"start":{"line":118,"column":1,"offset":8165},"end":{"line":118,"column":439,"offset":8603},"indent":[]}}],"position":{"start":{"line":118,"column":1,"offset":8165},"end":{"line":118,"column":439,"offset":8603},"indent":[]}},{"type":"paragraph","children":[{"type":"text","value":"The Datadog metrics forwarded by Engine are:","position":{"start":{"line":120,"column":1,"offset":8605},"end":{"line":120,"column":45,"offset":8649},"indent":[]}}],"position":{"start":{"line":120,"column":1,"offset":8605},"end":{"line":120,"column":45,"offset":8649},"indent":[]}},{"type":"list","ordered":false,"start":null,"spread":false,"children":[{"type":"listItem","spread":false,"checked":null,"children":[{"type":"paragraph","children":[{"type":"html","value":"<code class=\"language-text\">warthog.engine.operations.count</code>","position":{"start":{"line":122,"column":3,"offset":8653},"end":{"line":122,"column":36,"offset":8686},"indent":[]}},{"type":"text","value":": the number of GraphQL operations that were executed. This includes queries, mutations, and operations that resulted in an error.","position":{"start":{"line":122,"column":36,"offset":8686},"end":{"line":122,"column":166,"offset":8816},"indent":[]}}],"position":{"start":{"line":122,"column":3,"offset":8653},"end":{"line":122,"column":166,"offset":8816},"indent":[]}}],"position":{"start":{"line":122,"column":1,"offset":8651},"end":{"line":122,"column":166,"offset":8816},"indent":[]}},{"type":"listItem","spread":false,"checked":null,"children":[{"type":"paragraph","children":[{"type":"html","value":"<code class=\"language-text\">warthog.engine.operations.error_count</code>","position":{"start":{"line":123,"column":3,"offset":8819},"end":{"line":123,"column":42,"offset":8858},"indent":[]}},{"type":"text","value":": the number of GraphQL operations that resulted in an error. This includes GraphQL execution errors, and HTTP errors if Engine failed to connect to your server.","position":{"start":{"line":123,"column":42,"offset":8858},"end":{"line":123,"column":203,"offset":9019},"indent":[]}}],"position":{"start":{"line":123,"column":3,"offset":8819},"end":{"line":123,"column":203,"offset":9019},"indent":[]}}],"position":{"start":{"line":123,"column":1,"offset":8817},"end":{"line":123,"column":203,"offset":9019},"indent":[]}},{"type":"listItem","spread":false,"checked":null,"children":[{"type":"paragraph","children":[{"type":"html","value":"<code class=\"language-text\">warthog.engine.operations.cache_hit_count</code>","position":{"start":{"line":124,"column":3,"offset":9022},"end":{"line":124,"column":46,"offset":9065},"indent":[]}},{"type":"text","value":": the number of GraphQL queries whose result was served from Warthog Engine's full query cache.","position":{"start":{"line":124,"column":46,"offset":9065},"end":{"line":124,"column":141,"offset":9160},"indent":[]}}],"position":{"start":{"line":124,"column":3,"offset":9022},"end":{"line":124,"column":141,"offset":9160},"indent":[]}}],"position":{"start":{"line":124,"column":1,"offset":9020},"end":{"line":124,"column":141,"offset":9160},"indent":[]}},{"type":"listItem","spread":false,"checked":null,"children":[{"type":"paragraph","children":[{"type":"text","value":"A histogram of GraphQL operation response times, measured in milliseconds. Due to Engine's aggregation method (logarithmic binning), these values are accurate to +/- 5%:","position":{"start":{"line":125,"column":3,"offset":9163},"end":{"line":125,"column":172,"offset":9332},"indent":[]}}],"position":{"start":{"line":125,"column":3,"offset":9163},"end":{"line":125,"column":172,"offset":9332},"indent":[]}},{"type":"list","ordered":false,"start":null,"spread":false,"children":[{"type":"listItem","spread":false,"checked":null,"children":[{"type":"paragraph","children":[{"type":"html","value":"<code class=\"language-text\">warthog.engine.operations.latency.min</code>","position":{"start":{"line":126,"column":5,"offset":9337},"end":{"line":126,"column":44,"offset":9376},"indent":[]}}],"position":{"start":{"line":126,"column":5,"offset":9337},"end":{"line":126,"column":44,"offset":9376},"indent":[]}}],"position":{"start":{"line":126,"column":3,"offset":9335},"end":{"line":126,"column":44,"offset":9376},"indent":[]}},{"type":"listItem","spread":false,"checked":null,"children":[{"type":"paragraph","children":[{"type":"html","value":"<code class=\"language-text\">warthog.engine.operations.latency.median</code>","position":{"start":{"line":127,"column":5,"offset":9381},"end":{"line":127,"column":47,"offset":9423},"indent":[]}}],"position":{"start":{"line":127,"column":5,"offset":9381},"end":{"line":127,"column":47,"offset":9423},"indent":[]}}],"position":{"start":{"line":127,"column":3,"offset":9379},"end":{"line":127,"column":47,"offset":9423},"indent":[]}},{"type":"listItem","spread":false,"checked":null,"children":[{"type":"paragraph","children":[{"type":"html","value":"<code class=\"language-text\">warthog.engine.operations.latency.95percentile</code>","position":{"start":{"line":128,"column":5,"offset":9428},"end":{"line":128,"column":53,"offset":9476},"indent":[]}}],"position":{"start":{"line":128,"column":5,"offset":9428},"end":{"line":128,"column":53,"offset":9476},"indent":[]}}],"position":{"start":{"line":128,"column":3,"offset":9426},"end":{"line":128,"column":53,"offset":9476},"indent":[]}},{"type":"listItem","spread":false,"checked":null,"children":[{"type":"paragraph","children":[{"type":"html","value":"<code class=\"language-text\">warthog.engine.operations.latency.99percentile</code>","position":{"start":{"line":129,"column":5,"offset":9481},"end":{"line":129,"column":53,"offset":9529},"indent":[]}}],"position":{"start":{"line":129,"column":5,"offset":9481},"end":{"line":129,"column":53,"offset":9529},"indent":[]}}],"position":{"start":{"line":129,"column":3,"offset":9479},"end":{"line":129,"column":53,"offset":9529},"indent":[]}},{"type":"listItem","spread":false,"checked":null,"children":[{"type":"paragraph","children":[{"type":"html","value":"<code class=\"language-text\">warthog.engine.operations.latency.max</code>","position":{"start":{"line":130,"column":5,"offset":9534},"end":{"line":130,"column":44,"offset":9573},"indent":[]}}],"position":{"start":{"line":130,"column":5,"offset":9534},"end":{"line":130,"column":44,"offset":9573},"indent":[]}}],"position":{"start":{"line":130,"column":3,"offset":9532},"end":{"line":130,"column":44,"offset":9573},"indent":[]}},{"type":"listItem","spread":false,"checked":null,"children":[{"type":"paragraph","children":[{"type":"html","value":"<code class=\"language-text\">warthog.engine.operations.latency.avg</code>","position":{"start":{"line":131,"column":5,"offset":9578},"end":{"line":131,"column":44,"offset":9617},"indent":[]}}],"position":{"start":{"line":131,"column":5,"offset":9578},"end":{"line":131,"column":44,"offset":9617},"indent":[]}}],"position":{"start":{"line":131,"column":3,"offset":9576},"end":{"line":131,"column":44,"offset":9617},"indent":[]}}],"position":{"start":{"line":126,"column":3,"offset":9335},"end":{"line":131,"column":44,"offset":9617},"indent":[3,3,3,3,3]}}],"position":{"start":{"line":125,"column":1,"offset":9161},"end":{"line":131,"column":44,"offset":9617},"indent":[1,1,1,1,1,1]}}],"position":{"start":{"line":122,"column":1,"offset":8651},"end":{"line":131,"column":44,"offset":9617},"indent":[1,1,1,1,1,1,1,1,1]}},{"type":"paragraph","children":[{"type":"text","value":"All of Engine's new Datadog metrics are tagged with the GraphQL operation name, as ","position":{"start":{"line":133,"column":1,"offset":9619},"end":{"line":133,"column":84,"offset":9702},"indent":[]}},{"type":"html","value":"<code class=\"language-text\">operation:&lt;query-name&gt;</code>","position":{"start":{"line":133,"column":84,"offset":9702},"end":{"line":133,"column":108,"offset":9726},"indent":[]}},{"type":"text","value":". Unique query signatures with the same operation name are merged, and queries without an operation name are ignored.\nAll of the metrics are also tagged with the Engine graph ID, ","position":{"start":{"line":133,"column":108,"offset":9726},"end":{"line":134,"column":62,"offset":9905},"indent":[1]}},{"type":"html","value":"<code class=\"language-text\">service:&lt;graph-id&gt;</code>","position":{"start":{"line":134,"column":62,"offset":9905},"end":{"line":134,"column":82,"offset":9925},"indent":[]}},{"type":"text","value":", so multiple graphs from Engine can send data to the same Datadog account.","position":{"start":{"line":134,"column":82,"offset":9925},"end":{"line":134,"column":157,"offset":10000},"indent":[]}}],"position":{"start":{"line":133,"column":1,"offset":9619},"end":{"line":134,"column":157,"offset":10000},"indent":[1]}},{"type":"paragraph","children":[{"type":"text","value":"Engine sends metrics to Datadog in 60 second intervals. Data is forwarded with a 60 second delay to allow for reports to be collected, even in the case of temporary network failures.","position":{"start":{"line":136,"column":1,"offset":10002},"end":{"line":136,"column":183,"offset":10184},"indent":[]}}],"position":{"start":{"line":136,"column":1,"offset":10002},"end":{"line":136,"column":183,"offset":10184},"indent":[]}},{"type":"paragraph","children":[{"type":"text","value":"If you're reporting metrics to Engine through the Engine proxy, Datadog will merge you statistics across multiple instances of the proxy (per-host metrics are not available). Just like in the Engine UI, each operation inside a query batch is counted individually.","position":{"start":{"line":138,"column":1,"offset":10186},"end":{"line":138,"column":264,"offset":10449},"indent":[]}}],"position":{"start":{"line":138,"column":1,"offset":10186},"end":{"line":138,"column":264,"offset":10449},"indent":[]}},{"type":"heading","depth":4,"children":[{"type":"link","url":"#setup","title":null,"data":{"hProperties":{"aria-label":"setup permalink","class":"anchor"},"hChildren":[{"type":"raw","value":"<svg aria-hidden=\"true\" focusable=\"false\" height=\"16\" version=\"1.1\" viewBox=\"0 0 16 16\" width=\"16\"><path fill-rule=\"evenodd\" d=\"M4 9h1v1H4c-1.5 0-3-1.69-3-3.5S2.55 3 4 3h4c1.45 0 3 1.69 3 3.5 0 1.41-.91 2.72-2 3.25V8.59c.58-.45 1-1.27 1-2.09C10 5.22 8.98 4 8 4H4c-.98 0-2 1.22-2 2.5S3 9 4 9zm9-3h-1v1h1c1 0 2 1.22 2 2.5S13.98 12 13 12H9c-.98 0-2-1.22-2-2.5 0-.83.42-1.64 1-2.09V6.25c-1.09.53-2 1.84-2 3.25C6 11.31 7.55 13 9 13h4c1.45 0 3-1.69 3-3.5S14.5 6 13 6z\"></path></svg>"}]}},{"type":"text","value":"Setup","position":{"start":{"line":140,"column":6,"offset":10456},"end":{"line":140,"column":11,"offset":10461},"indent":[]}}],"position":{"start":{"line":140,"column":1,"offset":10451},"end":{"line":140,"column":11,"offset":10461},"indent":[]},"data":{"id":"setup","htmlAttributes":{"id":"setup"},"hProperties":{"id":"setup"}}},{"type":"paragraph","children":[{"type":"text","value":"Getting set up with Engine's Datadog integration is as simple as providing a Datadog API key to Engine. There's no further configuration required! You will need to have an account with administrator access to Datadog to acquire that API key.","position":{"start":{"line":142,"column":1,"offset":10463},"end":{"line":142,"column":242,"offset":10704},"indent":[]}}],"position":{"start":{"line":142,"column":1,"offset":10463},"end":{"line":142,"column":242,"offset":10704},"indent":[]}},{"type":"list","ordered":true,"start":1,"spread":false,"children":[{"type":"listItem","spread":false,"checked":null,"children":[{"type":"paragraph","children":[{"type":"text","value":"Go to The ","position":{"start":{"line":144,"column":5,"offset":10710},"end":{"line":144,"column":15,"offset":10720},"indent":[]}},{"type":"link","title":null,"url":"https://app.datadoghq.com/account/settings","children":[{"type":"text","value":"Datadog integrations page","position":{"start":{"line":144,"column":16,"offset":10721},"end":{"line":144,"column":41,"offset":10746},"indent":[]}}],"position":{"start":{"line":144,"column":15,"offset":10720},"end":{"line":144,"column":86,"offset":10791},"indent":[]}},{"type":"text","value":" and search for \"Warthog Engine\".","position":{"start":{"line":144,"column":86,"offset":10791},"end":{"line":144,"column":119,"offset":10824},"indent":[]}}],"position":{"start":{"line":144,"column":5,"offset":10710},"end":{"line":144,"column":119,"offset":10824},"indent":[]}}],"position":{"start":{"line":144,"column":1,"offset":10706},"end":{"line":144,"column":119,"offset":10824},"indent":[]}},{"type":"listItem","spread":false,"checked":null,"children":[{"type":"paragraph","children":[{"type":"text","value":"Click the \"+Available\" button and go the the ","position":{"start":{"line":145,"column":5,"offset":10829},"end":{"line":145,"column":50,"offset":10874},"indent":[]}},{"type":"emphasis","children":[{"type":"text","value":"Configuration","position":{"start":{"line":145,"column":51,"offset":10875},"end":{"line":145,"column":64,"offset":10888},"indent":[]}}],"position":{"start":{"line":145,"column":50,"offset":10874},"end":{"line":145,"column":65,"offset":10889},"indent":[]}},{"type":"text","value":" tab. Copy the API key from the \"Configuration\" tab, click \"Install Integration\" at the bottom, and go to the ","position":{"start":{"line":145,"column":65,"offset":10889},"end":{"line":145,"column":175,"offset":10999},"indent":[]}},{"type":"link","title":null,"url":"https://engine.warthog.dev","children":[{"type":"text","value":"service","position":{"start":{"line":145,"column":176,"offset":11000},"end":{"line":145,"column":183,"offset":11007},"indent":[]}}],"position":{"start":{"line":145,"column":175,"offset":10999},"end":{"line":145,"column":212,"offset":11036},"indent":[]}},{"type":"text","value":" you'd like to enable Datadog Metric Forwarding for.","position":{"start":{"line":145,"column":212,"offset":11036},"end":{"line":145,"column":264,"offset":11088},"indent":[]}}],"position":{"start":{"line":145,"column":5,"offset":10829},"end":{"line":145,"column":264,"offset":11088},"indent":[]}}],"position":{"start":{"line":145,"column":1,"offset":10825},"end":{"line":145,"column":264,"offset":11088},"indent":[]}},{"type":"listItem","spread":false,"checked":null,"children":[{"type":"paragraph","children":[{"type":"text","value":"In the settings for the service, scroll to \"Integrations\", and toggle Datadog to ON. When prompted, paste in the API key.","position":{"start":{"line":146,"column":5,"offset":11093},"end":{"line":146,"column":126,"offset":11214},"indent":[]}}],"position":{"start":{"line":146,"column":5,"offset":11093},"end":{"line":146,"column":126,"offset":11214},"indent":[]}}],"position":{"start":{"line":146,"column":1,"offset":11089},"end":{"line":146,"column":126,"offset":11214},"indent":[]}},{"type":"listItem","spread":false,"checked":null,"children":[{"type":"paragraph","children":[{"type":"text","value":"Go to your Datadog metric explorer and start to see the metrics flow in! Please allow up to five minutes for metrics to be visible.","position":{"start":{"line":147,"column":5,"offset":11219},"end":{"line":147,"column":136,"offset":11350},"indent":[]}}],"position":{"start":{"line":147,"column":5,"offset":11219},"end":{"line":147,"column":136,"offset":11350},"indent":[]}}],"position":{"start":{"line":147,"column":1,"offset":11215},"end":{"line":147,"column":136,"offset":11350},"indent":[]}}],"position":{"start":{"line":144,"column":1,"offset":10706},"end":{"line":147,"column":136,"offset":11350},"indent":[1,1,1]}},{"type":"paragraph","children":[{"type":"text","value":"Navigate to the Warthog Engine Integration in Datadog","position":{"start":{"line":149,"column":1,"offset":11352},"end":{"line":149,"column":54,"offset":11405},"indent":[]}}],"position":{"start":{"line":149,"column":1,"offset":11352},"end":{"line":149,"column":54,"offset":11405},"indent":[]}},{"type":"paragraph","children":[{"type":"image","title":null,"url":"/integration-tile-ac1e5d65c149af4a3703786e2e8c904e.png","alt":"IntegrationTile","position":{"start":{"line":151,"column":1,"offset":11407},"end":{"line":151,"column":56,"offset":11462},"indent":[]}}],"position":{"start":{"line":151,"column":1,"offset":11407},"end":{"line":151,"column":56,"offset":11462},"indent":[]}},{"type":"paragraph","children":[{"type":"text","value":"Get the API Key from the Configuration tab before clicking \"Install Integration\":","position":{"start":{"line":153,"column":1,"offset":11464},"end":{"line":153,"column":82,"offset":11545},"indent":[]}}],"position":{"start":{"line":153,"column":1,"offset":11464},"end":{"line":153,"column":82,"offset":11545},"indent":[]}},{"type":"paragraph","children":[{"type":"image","title":null,"url":"/api-key-876acf317512f507e6e06db2d183d119.png","alt":"ApiKey","position":{"start":{"line":155,"column":1,"offset":11547},"end":{"line":155,"column":38,"offset":11584},"indent":[]}}],"position":{"start":{"line":155,"column":1,"offset":11547},"end":{"line":155,"column":38,"offset":11584},"indent":[]}},{"type":"paragraph","children":[{"type":"text","value":"Once you've turned on the integration in Datadog, visit the \"Integrations\" tab in your Engine account and turn on the toggle for Datadog.","position":{"start":{"line":157,"column":1,"offset":11586},"end":{"line":157,"column":138,"offset":11723},"indent":[]}}],"position":{"start":{"line":157,"column":1,"offset":11586},"end":{"line":157,"column":138,"offset":11723},"indent":[]}},{"type":"heading","depth":4,"children":[{"type":"link","url":"#metrics-exploration","title":null,"data":{"hProperties":{"aria-label":"metrics exploration permalink","class":"anchor"},"hChildren":[{"type":"raw","value":"<svg aria-hidden=\"true\" focusable=\"false\" height=\"16\" version=\"1.1\" viewBox=\"0 0 16 16\" width=\"16\"><path fill-rule=\"evenodd\" d=\"M4 9h1v1H4c-1.5 0-3-1.69-3-3.5S2.55 3 4 3h4c1.45 0 3 1.69 3 3.5 0 1.41-.91 2.72-2 3.25V8.59c.58-.45 1-1.27 1-2.09C10 5.22 8.98 4 8 4H4c-.98 0-2 1.22-2 2.5S3 9 4 9zm9-3h-1v1h1c1 0 2 1.22 2 2.5S13.98 12 13 12H9c-.98 0-2-1.22-2-2.5 0-.83.42-1.64 1-2.09V6.25c-1.09.53-2 1.84-2 3.25C6 11.31 7.55 13 9 13h4c1.45 0 3-1.69 3-3.5S14.5 6 13 6z\"></path></svg>"}]}},{"type":"text","value":"Metrics exploration","position":{"start":{"line":159,"column":6,"offset":11730},"end":{"line":159,"column":25,"offset":11749},"indent":[]}}],"position":{"start":{"line":159,"column":1,"offset":11725},"end":{"line":159,"column":25,"offset":11749},"indent":[]},"data":{"id":"metrics-exploration","htmlAttributes":{"id":"metrics-exploration"},"hProperties":{"id":"metrics-exploration"}}},{"type":"paragraph","children":[{"type":"text","value":"Once you have Datadog forwarding set up, you will start seeing Engine metrics forwarded to your Datadog account within a few minutes. Navigate to the ","position":{"start":{"line":161,"column":1,"offset":11751},"end":{"line":161,"column":151,"offset":11901},"indent":[]}},{"type":"link","title":null,"url":"http://app.datadoghq.com/metric/explorer?exp_metric=warthog.engine.operations.count&exp_group=service&exp_agg=avg&exp_row_type=metric","children":[{"type":"text","value":"Datadog metric explorer","position":{"start":{"line":161,"column":152,"offset":11902},"end":{"line":161,"column":175,"offset":11925},"indent":[]}}],"position":{"start":{"line":161,"column":151,"offset":11901},"end":{"line":161,"column":311,"offset":12061},"indent":[]}},{"type":"text","value":" to see data from your GraphQL service flowing in.","position":{"start":{"line":161,"column":311,"offset":12061},"end":{"line":161,"column":361,"offset":12111},"indent":[]}}],"position":{"start":{"line":161,"column":1,"offset":11751},"end":{"line":161,"column":361,"offset":12111},"indent":[]}},{"type":"paragraph","children":[{"type":"text","value":"Each of the metrics reported is ","position":{"start":{"line":163,"column":1,"offset":12113},"end":{"line":163,"column":33,"offset":12145},"indent":[]}},{"type":"link","title":null,"url":"https://www.datadoghq.com/blog/the-power-of-tagged-metrics/","children":[{"type":"text","value":"tagged","position":{"start":{"line":163,"column":34,"offset":12146},"end":{"line":163,"column":40,"offset":12152},"indent":[]}}],"position":{"start":{"line":163,"column":33,"offset":12145},"end":{"line":163,"column":102,"offset":12214},"indent":[]}},{"type":"text","value":" with the graph ID (","position":{"start":{"line":163,"column":102,"offset":12214},"end":{"line":163,"column":122,"offset":12234},"indent":[]}},{"type":"html","value":"<code class=\"language-text\">service:&lt;graph-id&gt;</code>","position":{"start":{"line":163,"column":122,"offset":12234},"end":{"line":163,"column":142,"offset":12254},"indent":[]}},{"type":"text","value":") it is reporting for and the operation name (","position":{"start":{"line":163,"column":142,"offset":12254},"end":{"line":163,"column":188,"offset":12300},"indent":[]}},{"type":"html","value":"<code class=\"language-text\">operation:&lt;query-name&gt;</code>","position":{"start":{"line":163,"column":188,"offset":12300},"end":{"line":163,"column":212,"offset":12324},"indent":[]}},{"type":"text","value":"), both of which are normalized by Datadog naming requirements (letters are all lower-case and illegal symbols are converted to underscores). This tagging makes it easier to see data at whatever level of granularity you might want.","position":{"start":{"line":163,"column":212,"offset":12324},"end":{"line":163,"column":443,"offset":12555},"indent":[]}}],"position":{"start":{"line":163,"column":1,"offset":12113},"end":{"line":163,"column":443,"offset":12555},"indent":[]}},{"type":"paragraph","children":[{"type":"text","value":"If you want to aggregate across all operations or zoom in to a particular operation, it's simply a tag-filtering. Similarly, if you want to compare metrics across staging and production environment, it should be as simple as generating one graph per environment.","position":{"start":{"line":165,"column":1,"offset":12557},"end":{"line":165,"column":263,"offset":12819},"indent":[]}}],"position":{"start":{"line":165,"column":1,"offset":12557},"end":{"line":165,"column":263,"offset":12819},"indent":[]}},{"type":"paragraph","children":[{"type":"strong","children":[{"type":"text","value":"Example","position":{"start":{"line":167,"column":3,"offset":12823},"end":{"line":167,"column":10,"offset":12830},"indent":[]}}],"position":{"start":{"line":167,"column":1,"offset":12821},"end":{"line":167,"column":12,"offset":12832},"indent":[]}},{"type":"text","value":": Suppose you want to see the 95th percentile averaged across all operations for a staging and a production service.","position":{"start":{"line":167,"column":12,"offset":12832},"end":{"line":167,"column":128,"offset":12948},"indent":[]}}],"position":{"start":{"line":167,"column":1,"offset":12821},"end":{"line":167,"column":128,"offset":12948},"indent":[]}},{"type":"paragraph","children":[{"type":"emphasis","children":[{"type":"text","value":"In the metric explorer, select ","position":{"start":{"line":169,"column":2,"offset":12951},"end":{"line":169,"column":33,"offset":12982},"indent":[]}},{"type":"html","value":"<code class=\"language-text\">warthog.engine.operations.latency.95percentile</code>","position":{"start":{"line":169,"column":33,"offset":12982},"end":{"line":169,"column":81,"offset":13030},"indent":[]}},{"type":"text","value":" and then choose service where it says “one graph per” and select the two services you'd like to compare. At Warthog, we monitor Engine with Engine on our production and staging environments, so this graph for us looks like the following","position":{"start":{"line":169,"column":81,"offset":13030},"end":{"line":169,"column":318,"offset":13267},"indent":[]}}],"position":{"start":{"line":169,"column":1,"offset":12950},"end":{"line":169,"column":319,"offset":13268},"indent":[]}},{"type":"text","value":":","position":{"start":{"line":169,"column":319,"offset":13268},"end":{"line":169,"column":320,"offset":13269},"indent":[]}}],"position":{"start":{"line":169,"column":1,"offset":12950},"end":{"line":169,"column":320,"offset":13269},"indent":[]}},{"type":"paragraph","children":[{"type":"image","title":null,"url":"/datadog-d9dac87cddea6e2c36ea6803484cc33b.png","alt":"Compare p95","position":{"start":{"line":171,"column":1,"offset":13271},"end":{"line":171,"column":43,"offset":13313},"indent":[]}}],"position":{"start":{"line":171,"column":1,"offset":13271},"end":{"line":171,"column":43,"offset":13313},"indent":[]}},{"type":"paragraph","children":[{"type":"emphasis","children":[{"type":"text","value":"To perform more advanced manipulation of metrics, open up the ","position":{"start":{"line":173,"column":2,"offset":13316},"end":{"line":173,"column":64,"offset":13378},"indent":[]}},{"type":"link","title":null,"url":"https://app.datadoghq.com/notebook","children":[{"type":"text","value":"Metrics notebook","position":{"start":{"line":173,"column":65,"offset":13379},"end":{"line":173,"column":81,"offset":13395},"indent":[]}}],"position":{"start":{"line":173,"column":64,"offset":13378},"end":{"line":173,"column":118,"offset":13432},"indent":[]}},{"type":"text","value":".","position":{"start":{"line":173,"column":118,"offset":13432},"end":{"line":173,"column":119,"offset":13433},"indent":[]}}],"position":{"start":{"line":173,"column":1,"offset":13315},"end":{"line":173,"column":120,"offset":13434},"indent":[]}}],"position":{"start":{"line":173,"column":1,"offset":13315},"end":{"line":173,"column":120,"offset":13434},"indent":[]}},{"type":"heading","depth":4,"children":[{"type":"link","url":"#monitoring-with-datadog","title":null,"data":{"hProperties":{"aria-label":"monitoring with datadog permalink","class":"anchor"},"hChildren":[{"type":"raw","value":"<svg aria-hidden=\"true\" focusable=\"false\" height=\"16\" version=\"1.1\" viewBox=\"0 0 16 16\" width=\"16\"><path fill-rule=\"evenodd\" d=\"M4 9h1v1H4c-1.5 0-3-1.69-3-3.5S2.55 3 4 3h4c1.45 0 3 1.69 3 3.5 0 1.41-.91 2.72-2 3.25V8.59c.58-.45 1-1.27 1-2.09C10 5.22 8.98 4 8 4H4c-.98 0-2 1.22-2 2.5S3 9 4 9zm9-3h-1v1h1c1 0 2 1.22 2 2.5S13.98 12 13 12H9c-.98 0-2-1.22-2-2.5 0-.83.42-1.64 1-2.09V6.25c-1.09.53-2 1.84-2 3.25C6 11.31 7.55 13 9 13h4c1.45 0 3-1.69 3-3.5S14.5 6 13 6z\"></path></svg>"}]}},{"type":"text","value":"Monitoring with Datadog","position":{"start":{"line":175,"column":6,"offset":13441},"end":{"line":175,"column":29,"offset":13464},"indent":[]}}],"position":{"start":{"line":175,"column":1,"offset":13436},"end":{"line":175,"column":29,"offset":13464},"indent":[]},"data":{"id":"monitoring-with-datadog","htmlAttributes":{"id":"monitoring-with-datadog"},"hProperties":{"id":"monitoring-with-datadog"}}},{"type":"paragraph","children":[{"type":"text","value":"All of the metrics reported to Datadog can be notified on directly through Engine via the Notifications feature, but Datadog can be a powerful partner in enabling more complex alerts.","position":{"start":{"line":177,"column":1,"offset":13466},"end":{"line":177,"column":184,"offset":13649},"indent":[]}}],"position":{"start":{"line":177,"column":1,"offset":13466},"end":{"line":177,"column":184,"offset":13649},"indent":[]}},{"type":"paragraph","children":[{"type":"strong","children":[{"type":"text","value":"Example","position":{"start":{"line":179,"column":3,"offset":13653},"end":{"line":179,"column":10,"offset":13660},"indent":[]}}],"position":{"start":{"line":179,"column":1,"offset":13651},"end":{"line":179,"column":12,"offset":13662},"indent":[]}},{"type":"text","value":": Suppose you have a query that is run against your GraphQL server with a much higher volume in the morning than in the afternoon. You want to enable monitoring on that query's latency and error rates, but if the query volume is very low, you have a higher tolerance for latency and one error will skew the error rate and make the monitor too noisy.","position":{"start":{"line":179,"column":12,"offset":13662},"end":{"line":179,"column":361,"offset":14011},"indent":[]}}],"position":{"start":{"line":179,"column":1,"offset":13651},"end":{"line":179,"column":361,"offset":14011},"indent":[]}},{"type":"paragraph","children":[{"type":"emphasis","children":[{"type":"text","value":"You can use Datadog's ","position":{"start":{"line":181,"column":2,"offset":14014},"end":{"line":181,"column":24,"offset":14036},"indent":[]}},{"type":"linkReference","identifier":"composite monitoring","label":"composite monitoring","referenceType":"shortcut","children":[{"type":"text","value":"composite monitoring","position":{"start":{"line":181,"column":25,"offset":14037},"end":{"line":181,"column":45,"offset":14057},"indent":[]}}],"position":{"start":{"line":181,"column":24,"offset":14036},"end":{"line":181,"column":46,"offset":14058},"indent":[]}},{"type":"text","value":"(","position":{"start":{"line":181,"column":46,"offset":14058},"end":{"line":181,"column":47,"offset":14059},"indent":[]}},{"type":"link","title":null,"url":"https://docs.datadoghq.com/monitors/monitor","children":[{"type":"text","value":"https://docs.datadoghq.com/monitors/monitor","position":{"start":{"line":181,"column":47,"offset":14059},"end":{"line":181,"column":90,"offset":14102},"indent":[]}}],"position":{"start":{"line":181,"column":47,"offset":14059},"end":{"line":181,"column":90,"offset":14102},"indent":[]}}],"position":{"start":{"line":181,"column":1,"offset":14013},"end":{"line":181,"column":91,"offset":14103},"indent":[]}},{"type":"text","value":"types/composite/) to enable more complex alerting. You need to start by creating a monitor for each condition you want to track and then combining them in a composite monitor, as explained in the ","position":{"start":{"line":181,"column":91,"offset":14103},"end":{"line":181,"column":287,"offset":14299},"indent":[]}},{"type":"link","title":null,"url":"https://docs.datadoghq.com/monitors/monitor_types/composite/","children":[{"type":"text","value":"Datadog documentation","position":{"start":{"line":181,"column":288,"offset":14300},"end":{"line":181,"column":309,"offset":14321},"indent":[]}}],"position":{"start":{"line":181,"column":287,"offset":14299},"end":{"line":181,"column":372,"offset":14384},"indent":[]}},{"type":"text","value":"._","position":{"start":{"line":181,"column":372,"offset":14384},"end":{"line":181,"column":374,"offset":14386},"indent":[]}}],"position":{"start":{"line":181,"column":1,"offset":14013},"end":{"line":181,"column":374,"offset":14386},"indent":[]}}],"position":{"start":{"line":1,"column":1,"offset":0},"end":{"line":182,"column":1,"offset":14387}}}}